Workbook

Sheet INCOME STATEMENT
B2: YEAR | C2: ACTUAL | D2: ACTUAL | E2: ACTUAL | F2: ACTUAL | G2: ACTUAL | H2: ACTUAL | I2: ACTUAL | J2: FOCASTED | K2: FOCASTED | L2: FOCASTED | M2: FOCASTED | N2: FOCASTED | P2: ASSUMED VALUES | Q2: REASONING FOR ASSUMPTION
C3: 2019 | D3: 2020 | E3: 2021 | F3: 2022 | G3: 2023 | H3: 2024 | I3: 2025 | J3: 2026 | K3: 2027 | L3: 2028 | M3: 2029 | N3: 2030
B4: Revenue | C4: 2997.42 | D4: 3507.93 | E4: 5624.82 | F4: 8929 | G4: 11856 | H4: 14780 | I4: 17141 | J4: =I4*(1+J5) -> 20740.61 | K4: =J4*(1+K5) -> 24785.029 | L4: =K4*(1+L5) -> 29246.334 | M4: =L4*(1+M5) -> 34071.979 | N4: =M4*(1+N5) -> 39182.776 | Q4: VIEW ASSUMPTIONS AND REASONING FILE
B5: Growth | C5: 0 | D5: =(D4-C4)/C4 -> 0.17031647 | E5: =(E4-D4)/D4 -> 0.60345845 | F5: =(F4-E4)/E4 -> 0.58742858 | G5: =(G4-F4)/F4 -> 0.32780827 | H5: =(H4-G4)/G4 -> 0.24662618 | I5: =(I4-H4)/H4 -> 0.1597429 | J5: 0.21 | K5: =J5-0.015 -> 0.195 | L5: =K5-0.015 -> 0.18 | M5: =L5-0.015 -> 0.165 | N5: =M5-0.015 -> 0.15
B6: COGS | C6: 0 | D6: 0 | E6: 0 | F6: 0 | G6: 0 | H6: 0 | I6: 0 | J6: 0 | K6: 0 | L6: 0 | M6: 0 | N6: 0 | Q6: COGS: ₹0; SERVICE-BASED OPERATIONS.
B7: Gross Margins | C7: 1 | D7: 1 | E7: 1 | F7: 1 | G7: 1 | H7: 1 | I7: 1 | J7: 1 | K7: 1 | L7: 1 | M7: 1 | N7: 1
B8: Change in Inventory | C8: 0 | D8: 0 | E8: 0 | F8: 0 | G8: 0 | H8: 0 | I8: 0 | J8: 0 | K8: 0 | L8: 0 | M8: 0 | N8: 0 | Q8: NO INVENTORY
B10: Employee Benefit Expenses | F10: 689 | G10: 366 | H10: 460 | I10: 672 | J10: =J4*$P$10 -> 725.92135 | K10: =K4*$P$10 -> 867.47601 | L10: =L4*$P$10 -> 1023.6217 | M10: =M4*$P$10 -> 1192.5193 | N10: =N4*$P$10 -> 1371.3972 | P10: 0.035 | Q10: EMPLOYEE BENEFIT EXPENSES (% OF REVENUE): 3.5%; ASSUMED STABLE AT RECENT NORMALIZED HISTORICAL AVERAGE (FY2023-FY2025).
B11: Other Expenses | F11: 1740 | G11: 1859 | H11: 2709 | I11: 3588 | J11: =J4*$P$11 -> 4071.3817 | K11: =K4*$P$11 -> 4865.3012 | L11: =L4*$P$11 -> 5741.0554 | M11: =M4*$P$11 -> 6688.3295 | N11: =N4*$P$11 -> 7691.579 | P11: 0.1963 | Q11: VIEW ASSUMPTIONS AND REASONING FILE
B12: Total Operating expenses | C12: 1073.12 | D12: 1241.98 | E12: 1484.12 | F12: =SUM(F10:F11) -> 2429 | G12: =SUM(G10:G11) -> 2225 | H12: =SUM(H10:H11) -> 3169 | I12: =SUM(I10:I11) -> 4260 | J12: =SUM(J10:J11) -> 4797.3031 | K12: =SUM(K10:K11) -> 5732.7772 | L12: =SUM(L10:L11) -> 6764.6771 | M12: =SUM(M10:M11) -> 7880.8488 | N12: =SUM(N10:N11) -> 9062.9761 | Q12: SUM OF ABOVE
B14: Growth IN Operating Expenses | C14: 0 | D14: =(D12-C12)/C12 -> 0.15735426 | E14: =(E12-D12)/D12 -> 0.19496288 | F14: =(F12-E12)/E12 -> 0.63666011 | G14: =(G12-F12)/F12 -> -0.083985179 | H14: =(H12-G12)/G12 -> 0.42426966 | I14: =(I12-H12)/H12 -> 0.34427264 | J14: =(J12-I12)/I12 -> 0.12612749 | K14: =(K12-J12)/J12 -> 0.195 | ... N14: =(N12-M12)/M12 -> 0.15
B15: EBITDA / Operating Profit | C15: 1924.3 | D15: 2266.01 | E15: 4140.7 | F15: 6500 | G15: 9631 | H15: 11611 | I15: 12881 | J15: =J4-J12 -> 15943.307 | K15: =K4-K12 -> 19052.252 | L15: =L4-L12 -> 22481.657 | M15: =M4-M12 -> 26191.13 | N15: =N4-N12 -> 30119.8 | Q15: Revenue - Total Operating expenses
B16: ERROR CHECK EBITDA | C16: =C15-(C4-C12) -> 0 | D16: =D15-(D4-D12) -> 0.06 | E16: =E15-(E4-E12) -> 0 | F16: =F15-(F4-F12) -> 0 | G16: =G15-(G4-G12) -> 0 | H16: =H15-(H4-H12) -> 0 | I16: =I15-(I4-I12) -> 0 | J16: =J15-(J4-J12) -> 0 | ... N16: =N15-(N4-N12) -> 0
B18: OPM | C18: =C15/C4 -> 0.64198544 | D18: =D15/D4 -> 0.64596785 | E18: =E15/E4 -> 0.736148 | F18: =F15/F4 -> 0.72796506 | G18: =G15/G4 -> 0.81233131 | H18: =H15/H4 -> 0.78558863 | I18: =I15/I4 -> 0.75147308 | J18: =J15/J4 -> 0.7687 | ... N18: =N15/N4 -> 0.7687
B19: D&A | C19: 142.02 | D19: 180.78 | E19: 226.01 | F19: 338 | G19: 384 | H19: 439 | I19: 546.59 | J19: ='FORCAST SCHEDULES'!J7 -> 737.83614 | K19: ='FORCAST SCHEDULES'!K7 -> 915.00712 | L19: ='FORCAST SCHEDULES'!L7 -> 1112.3046 | M19: ='FORCAST SCHEDULES'!M7 -> 1330.3053 | N19: ='FORCAST SCHEDULES'!N7 -> 1568.1785 | Q19: VIEW FORCAST SCHEDULES
B20: EBIT | C20: =C15-C19 -> 1782.28 | D20: =D15-D19 -> 2085.23 | E20: =E15-E19 -> 3914.69 | F20: =F15-F19 -> 6162 | G20: =G15-G19 -> 9247 | H20: =H15-H19 -> 11172 | I20: =I15-I19 -> 12334.41 | J20: =J15-J19 -> 15205.471 | ... N20: =N15-N19 -> 28551.622 | Q20: EBITDA -D&A
B21: EBIT Margins | C21: =C20/C4 -> 0.59460469 | D21: =D20/D4 -> 0.59443318 | E21: =E20/E4 -> 0.69596716 | F21: =F20/F4 -> 0.69011087 | G21: =G20/G4 -> 0.77994265 | H21: =H20/H4 -> 0.75588633 | I21: =I20/I4 -> 0.71958521 | J21: =J20/J4 -> 0.73312553 | ... N21: =N20/N4 -> 0.72867786
B22: ERROR CHECK EBIT | C22: =C20-(C15-C19) -> 0 | D22: =D20-(D15-D19) -> 0 | E22: =E20-(E15-E19) -> 0 | F22: =F20-(F15-F19) -> 0 | G22: =G20-(G15-G19) -> 0 | H22: =H20-(H15-H19) -> 0 | I22: =I20-(I15-I19) -> 0 | J22: =J20-(J15-J19) -> 0 | ... N22: =N20-(N15-N19) -> 0
B24: Other Income | C24: 793.92 | D24: 502.16 | E24: 488.22 | F24: 736.42 | G24: 997.63 | H24: 1754.14 | I24: 2165.01 | J24: =I24*(1+$P$24) -> 2691.9734 | K24: =J24*(1+$P$24) -> 3347.1998 | L24: =K24*(1+$P$24) -> 4161.9082 | M24: =L24*(1+$P$24) -> 5174.9166 | N24: =M24*(1+$P$24) -> 6434.4914 | P24: 0.2434 | Q24: This rate is based on the average historical year-over-year growth of "Other Income" from FY2020-FY2025, reflecting the recent trend in this revenue stream.
B25: Contribution to Core SGF | C25: 0 | D25: 62.08 | E25: -62.08 | F25: 0 | G25: 203.45 | H25: 1741.97 | I25: 234.09 | J25: 0 | K25: 0 | L25: 0 | M25: 0 | N25: 0 | Q25: VIEW ASSUMPTIONS AND REASONING FILE
B26: PBT | C26: 2576.21 | D26: 2525.25 | E26: 4465.97 | F26: 6912 | G26: 10041 | H26: 11184 | I26: =15474.78+198 -> 15672.78 | J26: =J20+J24+J25 -> 17897.444 | K26: =K20+K24+K25 -> 21484.444 | L26: =L20+L24+L25 -> 25531.261 | M26: =M20+M24+M25 -> 30035.742 | N26: =N20+N24+N25 -> 34986.113
B27: PBT Margins | C27: =C26/C4 -> 0.85947582 | D27: =D26/D4 -> 0.71986898 | E27: =E26/E4 -> 0.79397563 | F27: =F26/F4 -> 0.77410684 | G27: =G26/G4 -> 0.84691296 | H27: =H26/H4 -> 0.75669824 | I27: =I26/I4 -> 0.91434455 | J27: =J26/J4 -> 0.86291793 | ... N27: =N26/N4 -> 0.8928952
B29: Tax | C29: 868.17 | D29: 640.47 | E29: 891.55 | F29: 1714 | G29: 2540 | H29: 2778 | I29: 3869 | J29: =J26*$P$29 -> 4474.3611 | K29: =K26*$P$29 -> 5371.1111 | L29: =L26*$P$29 -> 6382.8152 | M29: =M26*$P$29 -> 7508.9355 | N29: =N26*$P$29 -> 8746.5282 | P29: 0.25 | Q29: The 25% tax rate forecast is a stable, long-term assumption aligned with the company's FY2025 rate and typical for large, profitable Indian companies. This rate accounts for the standard 25% corporate tax base, surcharges, and a 4% cess, and is considered a simplified yet robust forecast despite the option for a lower 22% rate under Section 115BAA, which requires forgoing deductions.
B30: Tax % | C30: =C29/C26 -> 0.33699504 | D30: =D29/D26 -> 0.25362637 | E30: =E29/E26 -> 0.19963188 | F30: =F29/F26 -> 0.24797454 | G30: =G29/G26 -> 0.25296285 | H30: =H29/H26 -> 0.24839056 | I30: =I29/I26 -> 0.24686112 | J30: =J29/J26 -> 0.25 | ... N30: =N29/N26 -> 0.25
B32: Loss from Discounted Operations | C32: 0 | D32: 0 | E32: 0 | F32: 134.6 | G32: 145.9 | H32: 100.7 | I32: 581.94 | J32: 0 | K32: 0 | L32: 0 | M32: 0 | N32: 0 | Q32: VIEW ASSUMPTIONS AND REASONING FILE
B33: PAT | C33: =C26-C29-C32 -> 1708.04 | D33: =D26-D29-D32 -> 1884.78 | E33: =E26-E29-E32 -> 3574.42 | F33: =F26-F29-F32 -> 5063.4 | G33: =G26-G29-G32 -> 7355.1 | H33: =H26-H29-H32 -> 8305.3 | I33: =I26-I29-I32 -> 11221.84 | J33: =J26-J29-J32 -> 13423.083 | ... N33: =N26-N29-N32 -> 26239.585
B34: Growth | C34: 0 | D34: =(D33-C33)/C33 -> 0.10347533 | E34: =(E33-D33)/D33 -> 0.89646537 | F34: =(F33-E33)/E33 -> 0.41656548 | G34: =(G33-F33)/F33 -> 0.45260102 | H34: =(H33-G33)/G33 -> 0.12918927 | I34: =(I33-H33)/H33 -> 0.35116612 | J34: =(J33-I33)/I33 -> 0.19615706 | K34: =(K33-J33)/J33 -> 0.20041969 | ... N34: =(N33-M33)/M33 -> 0.16481601
B35: NPM | C35: =C33/C4 -> 0.56983673 | D35: =D33/D4 -> 0.53729122 | E35: =E33/E4 -> 0.63547278 | F35: =F33/F4 -> 0.56707358 | G35: =G33/G4 -> 0.62036943 | H35: =H33/H4 -> 0.56192828 | I35: =I33/I4 -> 0.65467826 | J35: =J33/J4 -> 0.64718845 | ... N35: =N33/N4 -> 0.6696714
B36: ERROR CHECK PAT | C36: =C33-(C26-C29-C32) -> 0 | D36: =D33-(D26-D29-D32) -> 0 | E36: =E33-(E26-E29-E32) -> 0 | F36: =F33-(F26-F29-F32) -> 0 | G36: =G33-(G26-G29-G32) -> 0 | H36: =H33-(H26-H29-H32) -> 0 | I36: =I33-(I26-I29-I32) -> 0 | J36: =J33-(J26-J29-J32) -> 0 | ... N36: =N33-(N26-N29-N32) -> 0
B38: Shares Outstading | C38: 247.5 | D38: =C38 -> 247.5 | E38: =D38 -> 247.5 | F38: =E38 -> 247.5 | G38: =F38 -> 247.5 | H38: =G38 -> 247.5 | I38: =H38 -> 247.5 | J38: =I38 -> 247.5 | K38: =J38 -> 247.5 | ... N38: =M38 -> 247.5 | Q38: VIEW ASSUMPTIONS AND REASONING FILE
B39: EPS | C39: =C33/C38 -> 6.9011717 | D39: =D33/D38 -> 7.6152727 | E39: =E33/E38 -> 14.442101 | F39: =F33/F38 -> 20.458182 | G39: =G33/G38 -> 29.717576 | H39: =H33/H38 -> 33.556768 | I39: =I33/I38 -> 45.340768 | J39: =J33/J38 -> 54.234679 | ... N39: =N33/N38 -> 106.01852

Sheet CASH FLOW
B2: YEAR | D2: ACTUAL | E2: ACTUAL | F2: ACTUAL | G2: ACTUAL | H2: ACTUAL | I2: ACTUAL | J2: ACTUAL | K2: FOCASTED | L2: FOCASTED | M2: FOCASTED | N2: FOCASTED | O2: FOCASTED | Q2: ASSUMED VALUES | R2: REASONING FOR ASSUMPTION
D3: 2019 | E3: 2020 | F3: 2021 | G3: 2022 | H3: 2023 | I3: 2024 | J3: 2025 | K3: 2026 | L3: 2027 | M3: 2028 | N3: 2029 | O3: 2030
C4: notes
B5: Cash from Operations
B6: Net Income / PAT | C6: from income statement | E6: ='INCOME STATEMENT'!D33 -> 1884.78 | F6: ='INCOME STATEMENT'!E33 -> 3574.42 | G6: ='INCOME STATEMENT'!F33 -> 5063.4 | H6: ='INCOME STATEMENT'!G33 -> 7355.1 | I6: ='INCOME STATEMENT'!H33 -> 8305.3 | J6: ='INCOME STATEMENT'!I33 -> 11221.84 | K6: ='INCOME STATEMENT'!J33 -> 13423.083 | L6: ='INCOME STATEMENT'!K33 -> 16113.333 | ... O6: ='INCOME STATEMENT'!N33 -> 26239.585
B7: D&A | C7: from income statement | E7: ='INCOME STATEMENT'!D19 -> 180.78 | F7: ='INCOME STATEMENT'!E19 -> 226.01 | G7: ='INCOME STATEMENT'!F19 -> 338 | H7: ='INCOME STATEMENT'!G19 -> 384 | I7: ='INCOME STATEMENT'!H19 -> 439 | J7: ='INCOME STATEMENT'!I19 -> 546.59 | K7: ='INCOME STATEMENT'!J19 -> 737.83614 | L7: ='INCOME STATEMENT'!K19 -> 915.00712 | ... O7: ='INCOME STATEMENT'!N19 -> 1568.1785
B8: Change in Trade Receivables | C8: prior year -current year | E8: =-('BALANCE SHEET'!D24-'BALANCE SHEET'!C24) -> -199.6 | F8: =-'BALANCE SHEET'!E24+'BALANCE SHEET'!D24 -> -346.47 | G8: =-'BALANCE SHEET'!F24+'BALANCE SHEET'!E24 -> -616.37 | H8: =-'BALANCE SHEET'!G24+'BALANCE SHEET'!F24 -> 25.74 | I8: =-'BALANCE SHEET'!H24+'BALANCE SHEET'!G24 -> -275.45 | J8: =-'BALANCE SHEET'!I24+'BALANCE SHEET'!H24 -> 352.45 | K8: =-'BALANCE SHEET'!J24+'BALANCE SHEET'!I24 -> -874.38074 | L8: =-'BALANCE SHEET'!K24+'BALANCE SHEET'!J24 -> -329.57682 | M8: =-'BALANCE SHEET'!L24+'BALANCE SHEET'!K24 -> -328.65627 | ... O8: =-'BALANCE SHEET'!N24+'BALANCE SHEET'!M24 -> -452.73726
B9: Change in Other Current Assets | C9: prior year -current year | E9: =-'BALANCE SHEET'!D26+'BALANCE SHEET'!C26 -> -4454.97 | F9: =-'BALANCE SHEET'!E26+'BALANCE SHEET'!D26 -> 1866.91 | G9: =-'BALANCE SHEET'!F26+'BALANCE SHEET'!E26 -> -2482.04 | H9: =-'BALANCE SHEET'!G26+'BALANCE SHEET'!F26 -> -555.44 | I9: =-'BALANCE SHEET'!H26+'BALANCE SHEET'!G26 -> -2560.61 | J9: =-'BALANCE SHEET'!I26+'BALANCE SHEET'!H26 -> -6390.91 | K9: =-'BALANCE SHEET'!J26+'BALANCE SHEET'!I26 -> 52.420359 | L9: =-'BALANCE SHEET'!K26+'BALANCE SHEET'!J26 -> -4347.9567 | ... O9: =-'BALANCE SHEET'!N26+'BALANCE SHEET'!M26 -> -5063.4586
B10: Change in Other Current Liabilities | C10: current year - prior year | E10: ='BALANCE SHEET'!D12-'BALANCE SHEET'!C12 -> 2915.59 | F10: ='BALANCE SHEET'!E12-'BALANCE SHEET'!D12 -> 1675.46 | G10: ='BALANCE SHEET'!F12-'BALANCE SHEET'!E12 -> 1929.94 | H10: ='BALANCE SHEET'!G12-'BALANCE SHEET'!F12 -> -5078.19 | I10: ='BALANCE SHEET'!H12-'BALANCE SHEET'!G12 -> 21641.62 | J10: ='BALANCE SHEET'!I12-'BALANCE SHEET'!H12 -> -5836.54 | K10: ='BALANCE SHEET'!J12-'BALANCE SHEET'!I12 -> 66.015773 | L10: ='BALANCE SHEET'!K12-'BALANCE SHEET'!J12 -> 248.20808 | ... O10: ='BALANCE SHEET'!N12-'BALANCE SHEET'!M12 -> 509.20028
B11: Change in Settlement Guarantee Fund [SGF] | C11: current year - prior year | E11: ='BALANCE SHEET'!D16-'BALANCE SHEET'!C16 -> 369.09 | F11: ='BALANCE SHEET'!E16-'BALANCE SHEET'!D16 -> 366.16 | G11: ='BALANCE SHEET'!F16-'BALANCE SHEET'!E16 -> 462.3 | H11: ='BALANCE SHEET'!G16-'BALANCE SHEET'!F16 -> 1028.57 | I11: ='BALANCE SHEET'!H16-'BALANCE SHEET'!G16 -> 3626.65 | J11: ='BALANCE SHEET'!I16-'BALANCE SHEET'!H16 -> 3165.06 | K11: ='BALANCE SHEET'!J16-'BALANCE SHEET'!I16 -> -1075.3537 | L11: ='BALANCE SHEET'!K16-'BALANCE SHEET'!J16 -> -553.35892 | ... O11: ='BALANCE SHEET'!N16-'BALANCE SHEET'!M16 -> 456.33531
B12: Change in other Non-Current Liabilities | C12: current year - prior year | E12: ='BALANCE SHEET'!D9-'BALANCE SHEET'!C9 -> 73.54 | F12: ='BALANCE SHEET'!E9-'BALANCE SHEET'!D9 -> -20.27 | G12: ='BALANCE SHEET'!F9-'BALANCE SHEET'!E9 -> 226.79 | H12: ='BALANCE SHEET'!G9-'BALANCE SHEET'!F9 -> -55.14 | I12: ='BALANCE SHEET'!H9-'BALANCE SHEET'!G9 -> 137.89 | J12: ='BALANCE SHEET'!I9-'BALANCE SHEET'!H9 -> 294.67 | K12: ='BALANCE SHEET'!J9-'BALANCE SHEET'!I9 -> 184.03476 | L12: ='BALANCE SHEET'!K9-'BALANCE SHEET'!J9 -> 366.00114 | ... O12: ='BALANCE SHEET'!N9-'BALANCE SHEET'!M9 -> 853.25879
B13: Total Cash from Operations | E13: =SUM(E6:E12) -> 769.21 | F13: =SUM(F6:F12) -> 7342.22 | G13: =SUM(G6:G12) -> 4922.02 | H13: =SUM(H6:H12) -> 3104.64 | I13: =SUM(I6:I12) -> 31314.4 | J13: =SUM(J6:J12) -> 3353.16 | K13: =SUM(K6:K12) -> 12513.656 | L13: =SUM(L6:L12) -> 12411.657 | ... O13: =SUM(O6:O12) -> 24110.362
B15: Cash from Investing
B16: Capex | C16: [(Ending Fixed Assets for Current Year - Ending Fixed Assets for Prior Year) + D&A for Current Year] [negative] | E16: =('BALANCE SHEET'!D20-'BALANCE SHEET'!C20)+'INCOME STATEMENT'!D19 -> 166.84 | F16: =('BALANCE SHEET'!E20-'BALANCE SHEET'!D20)+'INCOME STATEMENT'!E19 -> 390.02 | G16: =('BALANCE SHEET'!F20-'BALANCE SHEET'!E20)+'INCOME STATEMENT'!F19 -> 686.36 | H16: =('BALANCE SHEET'!G20-'BALANCE SHEET'!F20)+'INCOME STATEMENT'!G19 -> 300.52 | I16: =('BALANCE SHEET'!H20-'BALANCE SHEET'!G20)+'INCOME STATEMENT'!H19 -> 476.94 | J16: =('BALANCE SHEET'!I20-'BALANCE SHEET'!H20)+'INCOME STATEMENT'!I19 -> 1103.08 | K16: =('BALANCE SHEET'!J20-'BALANCE SHEET'!I20)+'INCOME STATEMENT'!J19 -> 1161.4742 | L16: =('BALANCE SHEET'!K20-'BALANCE SHEET'!J20)+'INCOME STATEMENT'!K19 -> 1387.9616 | ... O16: =('BALANCE SHEET'!N20-'BALANCE SHEET'!M20)+'INCOME STATEMENT'!N19 -> 2194.2355
B17: Change in Other Non-Current Assets | C17: -(Ending Other Non-Current Assets for Current Year - Ending Other Non-Current Assets for Prior Year) | E17: =-('BALANCE SHEET'!D21-'BALANCE SHEET'!C21) -> 585.9 | F17: =-('BALANCE SHEET'!E21-'BALANCE SHEET'!D21) -> -2612.09 | G17: =-('BALANCE SHEET'!F21-'BALANCE SHEET'!E21) -> -89.4 | H17: =-('BALANCE SHEET'!G21-'BALANCE SHEET'!F21) -> -4464.47 | I17: =-('BALANCE SHEET'!H21-'BALANCE SHEET'!G21) -> -8431.51 | J17: =-('BALANCE SHEET'!I21-'BALANCE SHEET'!H21) -> 381.38 | K17: =-('BALANCE SHEET'!J21-'BALANCE SHEET'!I21) -> -155.98625 | L17: =-('BALANCE SHEET'!K21-'BALANCE SHEET'!J21) -> -441.02157 | ... O17: =-('BALANCE SHEET'!N21-'BALANCE SHEET'!M21) -> -450.22471
B18: Changein Assets Classified as held for sale | C18: -(Ending Assets Held for Sale for Current Year - Ending Assets Held for Sale for Prior Year) | E18: =-('BALANCE SHEET'!D29-'BALANCE SHEET'!C29) -> -440 | F18: =-('BALANCE SHEET'!E29-'BALANCE SHEET'!D29) -> 440 | G18: =-('BALANCE SHEET'!F29-'BALANCE SHEET'!E29) -> 0 | H18: =-('BALANCE SHEET'!G29-'BALANCE SHEET'!F29) -> -786.21 | I18: =-('BALANCE SHEET'!H29-'BALANCE SHEET'!G29) -> -66.29 | J18: =-('BALANCE SHEET'!I29-'BALANCE SHEET'!H29) -> 614.1 | K18: =-('BALANCE SHEET'!J29-'BALANCE SHEET'!I29) -> 238.4 | L18: =-('BALANCE SHEET'!K29-'BALANCE SHEET'!J29) -> 0 | ... O18: =-('BALANCE SHEET'!N29-'BALANCE SHEET'!M29) -> 0
B20: Total Cash from Investing | E20: =E17+E18-E16 -> -20.94 | F20: =F17+F18-F16 -> -2562.11 | G20: =G17+G18-G16 -> -775.76 | H20: =H17+H18-H16 -> -5551.2 | I20: =I17+I18-I16 -> -8974.74 | J20: =J17+J18-J16 -> -107.6 | K20: =K17+K18-K16 -> -1079.0604 | L20: =L17+L18-L16 -> -1828.9832 | ... O20: =O17+O18-O16 -> -2644.4602
B22: Cash from Finance
B23: Net Change in Debt/Borrowings | C23: Ending "Borrowings" - Beginning "Borrowings" | E23: 0 | F23: 0 | G23: 0 | H23: 0 | I23: 0 | J23: 0 | K23: 0 | L23: 0 | M23: 0 | N23: 0 | O23: 0
B24: Net Cash from Equity Issuances/Repurchases | C24: (Cash Proceeds from New Shares Issued - Cash Paid for Shares Repurchased) | E24: 0 | F24: 0 | G24: 0 | H24: 0 | I24: 0 | J24: 0 | K24: 0 | L24: 0 | M24: 0 | N24: 0 | O24: 0
B25: Dividends Paid | C25: PAT - (Ending Total Equity - Beginning Total Equity) [due to prefrence shares being absent] [negative] | E25: ='INCOME STATEMENT'!D33-('BALANCE SHEET'!D7-'BALANCE SHEET'!C7) -> 1051.05 | F25: ='INCOME STATEMENT'!E33-('BALANCE SHEET'!E7-'BALANCE SHEET'!D7) -> 560.46 | G25: ='INCOME STATEMENT'!F33-('BALANCE SHEET'!F7-'BALANCE SHEET'!E7) -> 1281.07 | H25: ='INCOME STATEMENT'!G33-('BALANCE SHEET'!G7-'BALANCE SHEET'!F7) -> 2293 | I25: ='INCOME STATEMENT'!H33-('BALANCE SHEET'!H7-'BALANCE SHEET'!G7) -> 4811.8 | J25: ='INCOME STATEMENT'!I33-('BALANCE SHEET'!I7-'BALANCE SHEET'!H7)+198 -> 5040.39 | K25: ='FORCAST SCHEDULES'!J24 -> 5100.7716 | L25: ='FORCAST SCHEDULES'!K24 -> 6123.0667 | M25: ='FORCAST SCHEDULES'!L24 -> 7276.4093 | N25: ='FORCAST SCHEDULES'!M24 -> 8560.1864 | O25: ='FORCAST SCHEDULES'!N24 -> 9971.0422 | Q25: Values from Forcast Schedules | R25: The historical dividends paid for 2025 were adjusted to exclude the ₹198 crore non-cash capital transaction related to the conversion of preferred shares into common equity. This ensures the dividends accurately reflect the operational outflow and that the Reserves forecast reconciles.
B26: Capital Restructuring. | J26: 198
B27: Total Cash from Finance | E27: =E23+E24-E25 -> -1051.05 | F27: =F23+F24-F25 -> -560.46 | G27: =G23+G24-G25 -> -1281.07 | H27: =H23+H24-H25 -> -2293 | I27: =I23+I24-I25 -> -4811.8 | J27: =J23+J24-J25+J26 -> -4842.39 | K27: =K23+K24-K25+K26 -> -5100.7716 | L27: =L23+L24-L25+L26 -> -6123.0667 | M27: =M23+M24-M25+M26 -> -7276.4093 | N27: =N23+N24-N25+N26 -> -8560.1864 | O27: =O23+O24-O25+O26 -> -9971.0422
B29: Beginning Cash | E29: =D31 -> 9540.68 | F29: =E31 -> 9237.9 | G29: =F31 -> 13457.55 | H29: =G31 -> 16322.74 | I29: =H31 -> 11583.18 | J29: =I31 -> 29111.04 | K29: =J31 -> 27514.21 | L29: =K31 -> 33848.034 | ... O29: =N31 -> 55941.673
B30: Change in Cash | E30: =SUM(E13,E20,E27) -> -302.78 | F30: =SUM(F13,F20,F27) -> 4219.65 | G30: =SUM(G13,G20,G27) -> 2865.19 | H30: =SUM(H13,H20,H27) -> -4739.56 | I30: =SUM(I13,I20,I27) -> 17527.86 | J30: =SUM(J13,J20,J27) -> -1596.83 | K30: =SUM(K13,K20,K27) -> 6333.8237 | L30: =SUM(L13,L20,L27) -> 4459.6074 | ... O30: =SUM(O13,O20,O27) -> 11494.859
B31: Ending cash | D31: ='BALANCE SHEET'!C25 -> 9540.68 | E31: =E29+E30 -> 9237.9 | F31: =F29+F30 -> 13457.55 | G31: =G29+G30 -> 16322.74 | H31: =H29+H30 -> 11583.18 | I31: =I29+I30 -> 29111.04 | J31: =J29+J30 -> 27514.21 | K31: =K29+K30 -> 33848.034 | L31: =L29+L30 -> 38307.641 | ... O31: =O29+O30 -> 67436.532
B33: ERROR CHECK CASH FLOW | D33: =D31-'BALANCE SHEET'!C25 -> 0 | E33: =E31-'BALANCE SHEET'!D25 -> 0 | F33: =F31-'BALANCE SHEET'!E25 -> 0 | G33: =G31-'BALANCE SHEET'!F25 -> 0 | H33: =H31-'BALANCE SHEET'!G25 -> 0 | I33: =I31-'BALANCE SHEET'!H25 -> 0 | J33: =J31-'BALANCE SHEET'!I25 -> 0 | K33: =K31-'BALANCE SHEET'!J25 -> 0 | ... O33: =O31-'BALANCE SHEET'!N25 -> 0

Sheet BALANCE SHEET
B2: YEAR | C2: ACTUAL | D2: ACTUAL | E2: ACTUAL | F2: ACTUAL | G2: ACTUAL | H2: ACTUAL | I2: ACTUAL | J2: FOCASTED | K2: FOCASTED | L2: FOCASTED | M2: FOCASTED | N2: FOCASTED | P2: ASSUMED VALUES | Q2: REASONING FOR ASSUMPTION
C3: 2019 | D3: 2020 | E3: 2021 | F3: 2022 | G3: 2023 | H3: 2024 | I3: 2025 | J3: 2026 | K3: 2027 | L3: 2028 | M3: 2029 | N3: 2030
B4: Equity Capital | C4: 49.5 | D4: 49.5 | E4: 49.5 | F4: 49.5 | G4: 49.5 | H4: 49.5 | I4: =49.5 -> 49.5 | J4: =$P$4 -> 247.5 | K4: =$P$4 -> 247.5 | L4: =$P$4 -> 247.5 | M4: =$P$4 -> 247.5 | N4: =$P$4 -> 247.5 | P4: 247.5 | Q4: VIEW ASSUMPTIONS AND REASONING FILE
B5: Share premium | C5: 0 | D5: 0 | E5: 0 | F5: 0 | G5: 0 | H5: 0 | I5: 198 | J5: 0 | K5: 0 | L5: 0 | M5: 0 | N5: 0 | Q5: VIEW ASSUMPTIONS AND REASONING FILE
B6: Reserves | C6: 7738.76 | D6: 8572.49 | E6: 11586.45 | F6: 15368.78 | G6: 20430.88 | H6: 23924.38 | I6: =30105.83 -> 30105.83 | J6: ='FORCAST SCHEDULES'!J17 -> 38428.142 | K6: ='FORCAST SCHEDULES'!K17 -> 48418.408 | L6: ='FORCAST SCHEDULES'!L17 -> 60290.444 | M6: ='FORCAST SCHEDULES'!M17 -> 74257.064 | N6: ='FORCAST SCHEDULES'!N17 -> 90525.607 | P6: Values from Forcast Schedules
B7: Total Equity | C7: =SUM(C4:C6) -> 7788.26 | D7: =SUM(D4:D6) -> 8621.99 | E7: =SUM(E4:E6) -> 11635.95 | F7: =SUM(F4:F6) -> 15418.28 | G7: =SUM(G4:G6) -> 20480.38 | H7: =SUM(H4:H6) -> 23973.88 | I7: =SUM(I4:I6) -> 30353.33 | J7: =SUM(J4:J6) -> 38675.642 | ... N7: =SUM(N4:N6) -> 90773.107
B9: Other Non-current Liabilities | C9: 189.55 | D9: 263.09 | E9: 242.82 | F9: 469.61 | G9: 414.47 | H9: 552.36 | I9: 847.03 | J9: ='FORCAST SCHEDULES'!J29 -> 1031.0648 | K9: ='FORCAST SCHEDULES'!K29 -> 1397.0659 | L9: ='FORCAST SCHEDULES'!L29 -> 1903.4806 | M9: ='FORCAST SCHEDULES'!M29 -> 2493.2453 | N9: ='FORCAST SCHEDULES'!N29 -> 3346.504 | P9: Values from Forcast Schedules
B10: Total Non-Current Liabilities | C10: =SUM(C9:C9) -> 189.55 | D10: =SUM(D9:D9) -> 263.09 | E10: =SUM(E9:E9) -> 242.82 | F10: =SUM(F9:F9) -> 469.61 | G10: =SUM(G9:G9) -> 414.47 | H10: =SUM(H9:H9) -> 552.36 | I10: =SUM(I9:I9) -> 847.03 | J10: =SUM(J9:J9) -> 1031.0648 | ... N10: =SUM(N9:N9) -> 3346.504
B12: Other Current Liabilities | C12: 8942.89 | D12: 11858.48 | E12: 13533.94 | F12: 15463.88 | G12: 10385.69 | H12: 32027.31 | I12: 26190.77 | J12: ='FORCAST SCHEDULES'!J35 -> 26256.786 | K12: ='FORCAST SCHEDULES'!K35 -> 26504.994 | L12: ='FORCAST SCHEDULES'!L35 -> 26793.579 | M12: ='FORCAST SCHEDULES'!M35 -> 27222.171 | N12: ='FORCAST SCHEDULES'!N35 -> 27731.371 | P12: Values from Forcast Schedules
B13: Total Current Liabilities | C13: =SUM(C12:C12) -> 8942.89 | D13: =SUM(D12:D12) -> 11858.48 | E13: =SUM(E12:E12) -> 13533.94 | F13: =SUM(F12:F12) -> 15463.88 | G13: =SUM(G12:G12) -> 10385.69 | H13: =SUM(H12:H12) -> 32027.31 | I13: =SUM(I12:I12) -> 26190.77 | J13: =SUM(J12:J12) -> 26256.786 | ... N13: =SUM(N12:N12) -> 27731.371
B14: Total Liabilities | C14: =C10+C13 -> 9132.44 | D14: =D10+D13 -> 12121.57 | E14: =E10+E13 -> 13776.76 | F14: =F10+F13 -> 15933.49 | G14: =G10+G13 -> 10800.16 | H14: =H10+H13 -> 32579.67 | I14: =I10+I13 -> 27037.8 | J14: =J10+J13 -> 27287.851 | ... N14: =N10+N13 -> 31077.876
B16: Settlement Gaurantee Fund (SGF) | C16: 3057.68 | D16: 3426.77 | E16: 3792.93 | F16: 4255.23 | G16: 5283.8 | H16: 8910.45 | I16: 12075.51 | J16: ='FORCAST SCHEDULES'!J42 -> 11000.156 | K16: ='FORCAST SCHEDULES'!K42 -> 10446.797 | L16: ='FORCAST SCHEDULES'!L42 -> 11709.748 | M16: ='FORCAST SCHEDULES'!M42 -> 11743.256 | N16: ='FORCAST SCHEDULES'!N42 -> 12199.591 | P16: Values from Forcast Schedules
B18: Equity + Liabilities | C18: =SUM(C7,C14,C16) -> 19978.38 | D18: =SUM(D7,D14,D16) -> 24170.33 | E18: =SUM(E7,E14,E16) -> 29205.64 | F18: =SUM(F7,F14,F16) -> 35607 | G18: =SUM(G7,G14,G16) -> 36564.34 | H18: =SUM(H7,H14,H16) -> 65464 | I18: =SUM(I7,I14,I16) -> 69466.64 | J18: =SUM(J7,J14,J16) -> 76963.648 | ... N18: =SUM(N7,N14,N16) -> 134050.57 | P18: Values from Forcast Schedules
B20: Fixed Assets | C20: 645.75 | D20: 631.81 | E20: 795.82 | F20: 1144.18 | G20: 1060.7 | H20: 1098.64 | I20: 1655.13 | J20: ='FORCAST SCHEDULES'!J9 -> 2078.768 | K20: ='FORCAST SCHEDULES'!K9 -> 2551.7225 | L20: ='FORCAST SCHEDULES'!L9 -> 3077.2127 | M20: ='FORCAST SCHEDULES'!M9 -> 3654.9382 | N20: ='FORCAST SCHEDULES'!N9 -> 4280.9952 | P20: Values from Forcast Schedules
B21: Other Non Current Assets | C21: 5958.6 | D21: 5372.7 | E21: 7984.79 | F21: 8074.19 | G21: 12538.66 | H21: 20970.17 | I21: 20588.79 | J21: ='FORCAST SCHEDULES'!J49 -> 20744.776 | K21: ='FORCAST SCHEDULES'!K49 -> 21185.798 | L21: ='FORCAST SCHEDULES'!L49 -> 21577.52 | M21: ='FORCAST SCHEDULES'!M49 -> 21997.037 | N21: ='FORCAST SCHEDULES'!N49 -> 22447.262 | P21: Values from Forcast Schedules
B22: Total Non-Current assets | C22: =SUM(C20:C21) -> 6604.35 | D22: =SUM(D20:D21) -> 6004.51 | E22: =SUM(E20:E21) -> 8780.61 | F22: =SUM(F20:F21) -> 9218.37 | G22: =SUM(G20:G21) -> 13599.36 | H22: =SUM(H20:H21) -> 22068.81 | I22: =SUM(I20:I21) -> 22243.92 | J22: =SUM(J20:J21) -> 22823.544 | ... N22: =SUM(N20:N21) -> 26728.257
B24: Trade Receivables | C24: 452.51 | D24: 652.11 | E24: 998.58 | F24: 1614.95 | G24: 1589.21 | H24: 1864.66 | I24: 1512.21 | J24: ='FORCAST SCHEDULES'!J56 -> 2386.5907 | K24: ='FORCAST SCHEDULES'!K56 -> 2716.1676 | L24: ='FORCAST SCHEDULES'!L56 -> 3044.8238 | M24: ='FORCAST SCHEDULES'!M56 -> 3733.9155 | N24: ='FORCAST SCHEDULES'!N56 -> 4186.6528 | P24: Values from Forcast Schedules
B25: Cash and Cash Equivalent | C25: 9540.68 | D25: 9237.9 | E25: 13457.55 | F25: 16322.74 | G25: 11583.18 | H25: 29111.04 | I25: 27514.21 | J25: ='CASH FLOW'!K31 -> 33848.034 | K25: ='CASH FLOW'!L31 -> 38307.641 | L25: ='CASH FLOW'!M31 -> 45862.623 | M25: ='CASH FLOW'!N31 -> 55941.673 | N25: ='CASH FLOW'!O31 -> 67436.532 | P25: Values from Forcast Schedules
B26: Other Current assets | C26: 3380.84 | D26: 7835.81 | E26: 5968.9 | F26: 8450.94 | G26: 9006.38 | H26: 11566.99 | I26: =17957.9 -> 17957.9 | J26: ='FORCAST SCHEDULES'!J64 -> 17905.48 | K26: ='FORCAST SCHEDULES'!K64 -> 22253.436 | L26: ='FORCAST SCHEDULES'!L64 -> 27382.573 | M26: ='FORCAST SCHEDULES'!M64 -> 30635.673 | N26: ='FORCAST SCHEDULES'!N64 -> 35699.131 | P26: Values from Forcast Schedules
B27: Total Current Assets | C27: =SUM(C24:C26) -> 13374.03 | D27: =SUM(D24:D26) -> 17725.82 | E27: =SUM(E24:E26) -> 20425.03 | F27: =SUM(F24:F26) -> 26388.63 | G27: =SUM(G24:G26) -> 22178.77 | H27: =SUM(H24:H26) -> 42542.69 | I27: =SUM(I24:I26) -> 46984.32 | J27: =SUM(J24:J26) -> 54140.104 | ... N27: =SUM(N24:N26) -> 107322.32
B29: Assets classified as held for sale | C29: 0 | D29: 440 | E29: 0 | F29: 0 | G29: 786.21 | H29: 852.5 | I29: 238.4 | J29: 0 | K29: 0 | L29: 0 | M29: 0 | N29: 0 | P29: 0 | Q29: VIEW ASSUMPTIONS AND REASONING FILE
P30: Values from Forcast Schedules
B31: Total Assets | C31: =SUM(C29,C27,C22) -> 19978.38 | D31: =SUM(D29,D27,D22) -> 24170.33 | E31: =SUM(E29,E27,E22) -> 29205.64 | F31: =SUM(F29,F27,F22) -> 35607 | G31: =SUM(G29,G27,G22) -> 36564.34 | H31: =SUM(H29,H27,H22) -> 65464 | I31: =SUM(I29,I27,I22) -> 69466.64 | J31: =SUM(J29,J27,J22) -> 76963.648 | ... N31: =SUM(N29,N27,N22) -> 134050.57
B32: ERROR CHECK ASSET - [EQUITY + LIABILITIES] | C32: =C31-C18 -> 0 | D32: =D31-D18 -> 0 | E32: =E31-E18 -> 0 | F32: =F31-F18 -> 0 | G32: =G31-G18 -> 0 | H32: =H31-H18 -> 0 | I32: =I31-I18 -> 0 | J32: =J31-J18 -> 0 | ... N32: =N31-N18 -> 0

Sheet KEY RATIOS
B2: RATIOS / YEAR | C2: ACTUAL | D2: ACTUAL | E2: ACTUAL | F2: ACTUAL | G2: ACTUAL | H2: ACTUAL | I2: ACTUAL | J2: FOCASTED | K2: FOCASTED | L2: FOCASTED | M2: FOCASTED | N2: FOCASTED | P2: Formulas
C3: 2019 | D3: 2020 | E3: 2021 | F3: 2022 | G3: 2023 | H3: 2024 | I3: 2025 | J3: 2026 | K3: 2027 | L3: 2028 | M3: 2029 | N3: 2030
B5: Per share data
B6: Eps | C6: ='INCOME STATEMENT'!C33/'INCOME STATEMENT'!C38 -> 6.9011717 | D6: ='INCOME STATEMENT'!D33/'INCOME STATEMENT'!D38 -> 7.6152727 | E6: ='INCOME STATEMENT'!E33/'INCOME STATEMENT'!E38 -> 14.442101 | F6: ='INCOME STATEMENT'!F33/'INCOME STATEMENT'!F38 -> 20.458182 | G6: ='INCOME STATEMENT'!G33/'INCOME STATEMENT'!G38 -> 29.717576 | H6: ='INCOME STATEMENT'!H33/'INCOME STATEMENT'!H38 -> 33.556768 | I6: ='INCOME STATEMENT'!I33/'INCOME STATEMENT'!I38 -> 45.340768 | J6: ='INCOME STATEMENT'!J33/'INCOME STATEMENT'!J38 -> 54.234679 | ... N6: ='INCOME STATEMENT'!N33/'INCOME STATEMENT'!N38 -> 106.01852 | P6: Net Income / Total Shares Outstanding
B7: Bvps | C7: ='BALANCE SHEET'!C7/'INCOME STATEMENT'!C38 -> 31.467717 | D7: ='BALANCE SHEET'!D7/'INCOME STATEMENT'!D38 -> 34.836323 | E7: ='BALANCE SHEET'!E7/'INCOME STATEMENT'!E38 -> 47.013939 | F7: ='BALANCE SHEET'!F7/'INCOME STATEMENT'!F38 -> 62.296081 | G7: ='BALANCE SHEET'!G7/'INCOME STATEMENT'!G38 -> 82.74901 | H7: ='BALANCE SHEET'!H7/'INCOME STATEMENT'!H38 -> 96.864162 | I7: ='BALANCE SHEET'!I7/'INCOME STATEMENT'!I38 -> 122.63972 | J7: ='BALANCE SHEET'!J7/'INCOME STATEMENT'!J38 -> 156.26522 | ... N7: ='BALANCE SHEET'!N7/'INCOME STATEMENT'!N38 -> 366.76003 | P7: Shareholder's Equity / Total Shares Outstanding
B9: Liquidity ratios
B10: Current ratio | C10: ='BALANCE SHEET'!C27/'BALANCE SHEET'!C13 -> 1.4954931 | D10: ='BALANCE SHEET'!D27/'BALANCE SHEET'!D13 -> 1.4947801 | E10: ='BALANCE SHEET'!E27/'BALANCE SHEET'!E13 -> 1.509171 | F10: ='BALANCE SHEET'!F27/'BALANCE SHEET'!F13 -> 1.7064689 | G10: ='BALANCE SHEET'!G27/'BALANCE SHEET'!G13 -> 2.1355124 | H10: ='BALANCE SHEET'!H27/'BALANCE SHEET'!H13 -> 1.3283254 | I10: ='BALANCE SHEET'!I27/'BALANCE SHEET'!I13 -> 1.7939266 | J10: ='BALANCE SHEET'!J27/'BALANCE SHEET'!J13 -> 2.0619471 | ... N10: ='BALANCE SHEET'!N27/'BALANCE SHEET'!N13 -> 3.8700688 | P10: Current Assets / Current Liabilities
B11: Quick ratio | C11: =('BALANCE SHEET'!C24+'BALANCE SHEET'!C25)/'BALANCE SHEET'!C13 -> 1.1174453 | D11: =('BALANCE SHEET'!D24+'BALANCE SHEET'!D25)/'BALANCE SHEET'!D13 -> 0.83400318 | E11: =('BALANCE SHEET'!E24+'BALANCE SHEET'!E25)/'BALANCE SHEET'!E13 -> 1.0681391 | F11: =('BALANCE SHEET'!F24+'BALANCE SHEET'!F25)/'BALANCE SHEET'!F13 -> 1.1599734 | G11: =('BALANCE SHEET'!G24+'BALANCE SHEET'!G25)/'BALANCE SHEET'!G13 -> 1.2683211 | H11: =('BALANCE SHEET'!H24+'BALANCE SHEET'!H25)/'BALANCE SHEET'!H13 -> 0.96716521 | I11: =('BALANCE SHEET'!I24+'BALANCE SHEET'!I25)/'BALANCE SHEET'!I13 -> 1.1082691 | J11: =('BALANCE SHEET'!J24+'BALANCE SHEET'!J25)/'BALANCE SHEET'!J13 -> 1.3800099 | ... N11: =('BALANCE SHEET'!N24+'BALANCE SHEET'!N25)/'BALANCE SHEET'!N13 -> 2.5827495 | P11: (Current Assets - Inventory) / Current Liabilities
B13: Profitability ratio
B14: Gross profit margin | C14: ='INCOME STATEMENT'!C7 -> 1 | D14: ='INCOME STATEMENT'!D7 -> 1 | E14: ='INCOME STATEMENT'!E7 -> 1 | F14: ='INCOME STATEMENT'!F7 -> 1 | G14: ='INCOME STATEMENT'!G7 -> 1 | H14: ='INCOME STATEMENT'!H7 -> 1 | I14: ='INCOME STATEMENT'!I7 -> 1 | J14: ='INCOME STATEMENT'!J7 -> 1 | ... N14: ='INCOME STATEMENT'!N7 -> 1 | P14: Gross Profit / Revenue
B15: Operating profit margin or ebitda margin | C15: ='INCOME STATEMENT'!C15/'INCOME STATEMENT'!C4 -> 0.64198544 | D15: ='INCOME STATEMENT'!D15/'INCOME STATEMENT'!D4 -> 0.64596785 | E15: ='INCOME STATEMENT'!E15/'INCOME STATEMENT'!E4 -> 0.736148 | F15: ='INCOME STATEMENT'!F15/'INCOME STATEMENT'!F4 -> 0.72796506 | G15: ='INCOME STATEMENT'!G15/'INCOME STATEMENT'!G4 -> 0.81233131 | H15: ='INCOME STATEMENT'!H15/'INCOME STATEMENT'!H4 -> 0.78558863 | I15: ='INCOME STATEMENT'!I15/'INCOME STATEMENT'!I4 -> 0.75147308 | J15: ='INCOME STATEMENT'!J15/'INCOME STATEMENT'!J4 -> 0.7687 | ... N15: ='INCOME STATEMENT'!N15/'INCOME STATEMENT'!N4 -> 0.7687 | P15: Operating Income / Revenue
B16: Ebit margin | C16: ='INCOME STATEMENT'!C21 -> 0.59460469 | D16: ='INCOME STATEMENT'!D21 -> 0.59443318 | E16: ='INCOME STATEMENT'!E21 -> 0.69596716 | F16: ='INCOME STATEMENT'!F21 -> 0.69011087 | G16: ='INCOME STATEMENT'!G21 -> 0.77994265 | H16: ='INCOME STATEMENT'!H21 -> 0.75588633 | I16: ='INCOME STATEMENT'!I21 -> 0.71958521 | J16: ='INCOME STATEMENT'!J21 -> 0.73312553 | ... N16: ='INCOME STATEMENT'!N21 -> 0.72867786 | P16: EBIT / Revenue
B17: Net profit margin | C17: ='INCOME STATEMENT'!C35 -> 0.56983673 | D17: ='INCOME STATEMENT'!D35 -> 0.53729122 | E17: ='INCOME STATEMENT'!E35 -> 0.63547278 | F17: ='INCOME STATEMENT'!F35 -> 0.56707358 | G17: ='INCOME STATEMENT'!G35 -> 0.62036943 | H17: ='INCOME STATEMENT'!H35 -> 0.56192828 | I17: ='INCOME STATEMENT'!I35 -> 0.65467826 | J17: ='INCOME STATEMENT'!J35 -> 0.64718845 | ... N17: ='INCOME STATEMENT'!N35 -> 0.6696714 | P17: Net Income / Revenue
B18: Roe | C18: ='INCOME STATEMENT'!C33/'BALANCE SHEET'!C7 -> 0.21930958 | D18: ='INCOME STATEMENT'!D33*2/('BALANCE SHEET'!C7+'BALANCE SHEET'!D7) -> 0.22970765 | E18: ='INCOME STATEMENT'!E33*2/('BALANCE SHEET'!D7+'BALANCE SHEET'!E7) -> 0.35289077 | F18: ='INCOME STATEMENT'!F33*2/('BALANCE SHEET'!F7+'BALANCE SHEET'!E7) -> 0.37431485 | G18: ='INCOME STATEMENT'!G33*2/('BALANCE SHEET'!G7+'BALANCE SHEET'!F7) -> 0.40977017 | H18: ='INCOME STATEMENT'!H33*2/('BALANCE SHEET'!H7+'BALANCE SHEET'!G7) -> 0.37365598 | I18: ='INCOME STATEMENT'!I33*2/('BALANCE SHEET'!I7+'BALANCE SHEET'!H7) -> 0.41312042 | J18: ='INCOME STATEMENT'!J33*2/('BALANCE SHEET'!J7+'BALANCE SHEET'!I7) -> 0.38891158 | K18: ='INCOME STATEMENT'!K33*2/('BALANCE SHEET'!K7+'BALANCE SHEET'!J7) -> 0.36897292 | L18: ='INCOME STATEMENT'!L33*2/('BALANCE SHEET'!L7+'BALANCE SHEET'!K7) -> 0.35069176 | M18: ='INCOME STATEMENT'!M33*2/('BALANCE SHEET'!M7+'BALANCE SHEET'!L7) -> 0.33362541 | N18: ='INCOME STATEMENT'!N33*2/('BALANCE SHEET'!N7+'BALANCE SHEET'!M7) -> 0.31752123 | P18: Net Income / Shareholder's Equity
B19: Roa | C19: ='INCOME STATEMENT'!C33/('BALANCE SHEET'!C31) -> 0.085494419 | D19: ='INCOME STATEMENT'!D33*2/('BALANCE SHEET'!D31+'BALANCE SHEET'!C31) -> 0.085383242 | E19: ='INCOME STATEMENT'!E33*2/('BALANCE SHEET'!E31+'BALANCE SHEET'!D31) -> 0.13393368 | F19: ='INCOME STATEMENT'!F33*2/('BALANCE SHEET'!F31+'BALANCE SHEET'!E31) -> 0.1562473 | G19: ='INCOME STATEMENT'!G33*2/('BALANCE SHEET'!G31+'BALANCE SHEET'!F31) -> 0.20382329 | H19: ='INCOME STATEMENT'!H33*2/('BALANCE SHEET'!H31+'BALANCE SHEET'!G31) -> 0.16280379 | I19: ='INCOME STATEMENT'!I33*2/('BALANCE SHEET'!I31+'BALANCE SHEET'!H31) -> 0.16633494 | J19: ='INCOME STATEMENT'!J33*2/('BALANCE SHEET'!J31+'BALANCE SHEET'!I31) -> 0.18333752 | K19: ='INCOME STATEMENT'!K33*2/('BALANCE SHEET'!K31+'BALANCE SHEET'!J31) -> 0.19652993 | ... N19: ='INCOME STATEMENT'!N33*2/('BALANCE SHEET'!N31+'BALANCE SHEET'!M31) -> 0.20990508 | P19: Net Income / Total Assets
B21: Efficiency Ratios
B22: Days Sales Outstanding (DSO): | C22: =ROUND(('BALANCE SHEET'!C24/'INCOME STATEMENT'!C4)*365,0) -> 55 | D22: =ROUND(('BALANCE SHEET'!D24/'INCOME STATEMENT'!D4)*365,0) -> 68 | E22: =ROUND(('BALANCE SHEET'!E24/'INCOME STATEMENT'!E4)*365,0) -> 65 | F22: =ROUND(('BALANCE SHEET'!F24/'INCOME STATEMENT'!F4)*365,0) -> 66 | G22: =ROUND(('BALANCE SHEET'!G24/'INCOME STATEMENT'!G4)*365,0) -> 49 | H22: =ROUND(('BALANCE SHEET'!H24/'INCOME STATEMENT'!H4)*365,0) -> 46 | I22: =ROUND(('BALANCE SHEET'!I24/'INCOME STATEMENT'!I4)*365,0) -> 32 | J22: =ROUND(('BALANCE SHEET'!J24/'INCOME STATEMENT'!J4)*365,0) -> 42 | ... N22: =ROUND(('BALANCE SHEET'!N24/'INCOME STATEMENT'!N4)*365,0) -> 39 | P22: (Accounts Receivable / Revenue) * 365

Sheet Comparable Company Analysis (CC
B1: All market data as of the close of business on September 20, 2025
B2: Source: Yahoo Finance, as of September 20, 2025
B4: Metric | C4: NSE (2026 - Projected) | D4: BSE | E4: MCX | F4: CDSL | G4: Median
B5: Revenue | C5: ='INCOME STATEMENT'!J4 -> 20740.61 | D5: 3313.86 | E5: 1133.33 | F5: 1083.63 | G5: =MEDIAN(C5:F5) -> 2223.595
B6: Net Income | C6: ='INCOME STATEMENT'!J33 -> 13423.083 | D6: 1584.92 | E6: 652.31 | F6: 494.8 | G6: =MEDIAN(C6:F6) -> 1118.615
B7: Totall Assets | C7: ='BALANCE SHEET'!J31 -> 76963.648 | D7: 10341.65 | E7: 4325.17 | F7: 2162.14 | G7: =MEDIAN(C7:F7) -> 7333.41
B8: Total Equity | C8: ='BALANCE SHEET'!J7 -> 38675.642 | D8: 4575.7 | E8: 1884.4 | F8: 1803.87 | G8: =MEDIAN(C8:F8) -> 3230.05
B9: P/E Ratio (TTM) | D9: 56.37 | E9: 62.93 | F9: 66.81 | G9: =MEDIAN(C9:F9) -> 62.93
B10: P/B Ratio | D10: 20.04 | E10: 21.74 | F10: 18.78 | G10: =MEDIAN(C10:F10) -> 20.04
B11: EV/Sales | D11: 25.9 | E11: 39.74 | F11: 29.63 | G11: =MEDIAN(C11:F11) -> 29.63
B12: EV/EBITDA | D12: 38.92 | E12: 51.75 | F12: 44.23 | G12: =MEDIAN(C12:F12) -> 44.23
B13: Net Profit Margin | D13: =D6/D5 -> 0.47827005 | E13: =E6/E5 -> 0.57556934 | F13: =F6/F5 -> 0.45661342 | G13: =MEDIAN(C13:F13) -> 0.47827005
B14: ROE | D14: =D6/D8 -> 0.3463776 | E14: =E6/E8 -> 0.34616323 | F14: =F6/F8 -> 0.27429915 | G14: =MEDIAN(C14:F14) -> 0.34616323
B15: ROA | D15: =D6/D7 -> 0.15325601 | E15: =E6/E7 -> 0.15081719 | F15: =F6/F7 -> 0.22884735 | G15: =MEDIAN(C15:F15) -> 0.15325601
E18: Formulas
B19: Enterprise Value (EV) of NSE [CCA] | C19: =G12*'INCOME STATEMENT'!J15 -> 705172.46 | E19: Median EV/EBITDA (from your table) x NSE's Projected EBITDA
B20: Equity Value (P/E) Calculation of NSE [CCA] | C20: =G9*C6 -> 844714.62 | E20: Median P/E×Projected Net Income

Sheet Final Valuation Summary
B3: Final Valuation Summary | F3: Formulas
B4: Valuation Method | C4: Valuation Type | D4: NSE Value (in ₹ crores)
B5: Discounted Cash Flow (DCF) | C5: Enterprise Value | D5: =('WACC AND DCF CALCULATION'!C69+'WACC AND DCF CALCULATION'!F69)/2 -> 1108272.1 | F5: Final DCF Value = (Perpetuity Growth Case EV + Exit Multiple Case EV) / 2
B6: Discounted Cash Flow (DCF) | C6: Equity Value | D6: =D5 -> 1108272.1
B7: Comparable Company Analysis (CCA) | C7: Enterprise Value | D7: ='Comparable Company Analysis (CC'!C19 -> 705172.46
B8: Comparable Company Analysis (CCA) | C8: Equity Value | D8: ='Comparable Company Analysis (CC'!C20 -> 844714.62
B9: Discounted Cash Flow (DCF) | C9: Implied Share | D9: =D5/'INCOME STATEMENT'!J38 -> 4477.8669 | F9: Equity Value / Shares Outstanding
B10: Comparable Company Analysis (CCA) | C10: Implied Share | D10: =D8/'INCOME STATEMENT'!J38 -> 3412.9884 | F10: Equity Value / Shares Outstanding
B13: Final Conclusion | C13: Value
B14: DCF Valuation | C14: =D9 -> 4477.8669
B15: CCA Valuation | C15: =D10 -> 3412.9884
B16: Final Target Price (Simple Average) | C16: =AVERAGE(C14:C15) -> 3945.4276

Sheet FORCAST SCHEDULES
B2: Capex Forcasting | C2: ACTUAL | D2: ACTUAL | E2: ACTUAL | F2: ACTUAL | G2: ACTUAL | H2: ACTUAL | I2: ACTUAL | J2: FOCASTED | K2: FOCASTED | L2: FOCASTED | M2: FOCASTED | N2: FOCASTED | P2: ASSUMED VALUES | Q2: REASONING FOR ASSUMPTION
C3: 2019 | D3: 2020 | E3: 2021 | F3: 2022 | G3: 2023 | H3: 2024 | I3: 2025 | J3: 2026 | K3: 2027 | L3: 2028 | M3: 2029 | N3: 2030
B4: Beginning Net Fixed Assets | D4: =C9 -> 645.75 | E4: =D9 -> 631.81 | F4: =E9 -> 795.82 | G4: =F9 -> 1144.18 | H4: =G9 -> 1060.7 | I4: =H9 -> 1098.64 | J4: =I9 -> 1655.13 | K4: =J9 -> 2078.768 | ... N4: =M9 -> 3654.9382
B5: Capex | D5: =D9-D4+D7 -> 166.84 | E5: =E9-E4+E7 -> 390.02 | F5: =F9-F4+F7 -> 686.36 | G5: =G9-G4+G7 -> 300.52 | H5: =H9-H4+H7 -> 476.94 | I5: =I9-I4+I7 -> 1103.08 | J5: =$P$5*'INCOME STATEMENT'!J4 -> 1161.4742 | K5: =$P$5*'INCOME STATEMENT'!K4 -> 1387.9616 | L5: =$P$5*'INCOME STATEMENT'!L4 -> 1637.7947 | M5: =$P$5*'INCOME STATEMENT'!M4 -> 1908.0308 | N5: =$P$5*'INCOME STATEMENT'!N4 -> 2194.2355 | P5: 0.056 | Q5: Median of last 6 Historical values
B6: Capex as part of Revenue | D6: =D5/'INCOME STATEMENT'!D4 -> 0.047560812 | E6: =E5/'INCOME STATEMENT'!E4 -> 0.069339108 | F6: =F5/'INCOME STATEMENT'!F4 -> 0.07686863 | G6: =G5/'INCOME STATEMENT'!G4 -> 0.025347503 | H6: =H5/'INCOME STATEMENT'!H4 -> 0.032269283 | I6: =I5/'INCOME STATEMENT'!I4 -> 0.064353305 | J6: =J5/'INCOME STATEMENT'!J4 -> 0.056 | K6: =K5/'INCOME STATEMENT'!K4 -> 0.056 | ... N6: =N5/'INCOME STATEMENT'!N4 -> 0.056
B7: D&A | D7: ='INCOME STATEMENT'!D19 -> 180.78 | E7: ='INCOME STATEMENT'!E19 -> 226.01 | F7: ='INCOME STATEMENT'!F19 -> 338 | G7: ='INCOME STATEMENT'!G19 -> 384 | H7: ='INCOME STATEMENT'!H19 -> 439 | I7: ='INCOME STATEMENT'!I19 -> 546.59 | J7: =$P$7*(J4+0.5*J5) -> 737.83614 | K7: =$P$7*(K4+0.5*K5) -> 915.00712 | L7: =$P$7*(L4+0.5*L5) -> 1112.3046 | M7: =$P$7*(M4+0.5*M5) -> 1330.3053 | N7: =$P$7*(N4+0.5*N5) -> 1568.1785 | P7: 0.33 | Q7: Depreciation & Amortization (D&A) for the forecast period is projected at 33.0% of an average depreciable asset base. This base is calculated as Beginning Net Fixed Assets + (0.5 * CAPEX) to ensure the D&A forecast is fundamentally linked to both the existing asset base and new capital investments. The 0.5 * CAPEX component incorporates a standard mid-year convention, assuming that new assets acquired during the year are, on average, in service for half of that period. The 33.0% rate itself was chosen because it reflects the stable recent historical average of this specific calculation for NSE over the FY2023-FY2025 period, providing a robust, data-driven basis for the forecast.
B8: D&A Rate (as % of Avg. Base) | D8: =D7/(D4+0.5*D5) -> 0.24792572 | E8: =E7/(E4+0.5*E5) -> 0.27334849 | F8: =F7/(F4+0.5*F5) -> 0.29675154 | G8: =G7/(G4+0.5*G5) -> 0.29665338 | H8: =H7/(H4+0.5*H5) -> 0.33790805 | I8: =I7/(I4+0.5*I5) -> 0.33123053 | J8: =J7/(J4+0.5*J5) -> 0.33 | K8: =K7/(K4+0.5*K5) -> 0.33 | ... N8: =N7/(N4+0.5*N5) -> 0.33
B9: Ending Net fixed Assets | C9: ='BALANCE SHEET'!C20 -> 645.75 | D9: ='BALANCE SHEET'!D20 -> 631.81 | E9: ='BALANCE SHEET'!E20 -> 795.82 | F9: ='BALANCE SHEET'!F20 -> 1144.18 | G9: ='BALANCE SHEET'!G20 -> 1060.7 | H9: ='BALANCE SHEET'!H20 -> 1098.64 | I9: ='BALANCE SHEET'!I20 -> 1655.13 | J9: =J4+J5-J7 -> 2078.768 | K9: =K4+K5-K7 -> 2551.7225 | L9: =L4+L5-L7 -> 3077.2127 | M9: =M4+M5-M7 -> 3654.9382 | N9: =N4+N5-N7 -> 4280.9952
B12: Reserve Forcasting | C12: ACTUAL | D12: ACTUAL | E12: ACTUAL | F12: ACTUAL | G12: ACTUAL | H12: ACTUAL | I12: ACTUAL | J12: FOCASTED | K12: FOCASTED | L12: FOCASTED | M12: FOCASTED | N12: FOCASTED
C13: 2019 | D13: 2020 | E13: 2021 | F13: 2022 | G13: 2023 | H13: 2024 | I13: 2025 | J13: 2026 | K13: 2027 | L13: 2028 | M13: 2029 | N13: 2030
B14: Beginning Reserves | D14: =C17 -> 7738.76 | E14: =D17 -> 8572.49 | F14: =E17 -> 11586.45 | G14: =F17 -> 15368.78 | H14: =G17 -> 20430.88 | I14: =H17 -> 23924.38 | J14: =I17 -> 30105.83 | K14: =J17 -> 38428.142 | ... N14: =M17 -> 74257.064
B15: PLUS: Net Income | D15: ='INCOME STATEMENT'!D33 -> 1884.78 | E15: ='INCOME STATEMENT'!E33 -> 3574.42 | F15: ='INCOME STATEMENT'!F33 -> 5063.4 | G15: ='INCOME STATEMENT'!G33 -> 7355.1 | H15: ='INCOME STATEMENT'!H33 -> 8305.3 | I15: ='INCOME STATEMENT'!I33 -> 11221.84 | J15: ='INCOME STATEMENT'!J33 -> 13423.083 | K15: ='INCOME STATEMENT'!K33 -> 16113.333 | ... N15: ='INCOME STATEMENT'!N33 -> 26239.585
B16: LESS: Dividends Paid | D16: ='CASH FLOW'!E25 -> 1051.05 | E16: ='CASH FLOW'!F25 -> 560.46 | F16: ='CASH FLOW'!G25 -> 1281.07 | G16: ='CASH FLOW'!H25 -> 2293 | H16: ='CASH FLOW'!I25 -> 4811.8 | I16: ='CASH FLOW'!J25 -> 5040.39 | J16: ='CASH FLOW'!K25 -> 5100.7716 | K16: ='CASH FLOW'!L25 -> 6123.0667 | ... N16: ='CASH FLOW'!O25 -> 9971.0422
B17: Ending Reserves | C17: ='BALANCE SHEET'!C6 -> 7738.76 | D17: =D14+D15-D16 -> 8572.49 | E17: =E14+E15-E16 -> 11586.45 | F17: =F14+F15-F16 -> 15368.78 | G17: =G14+G15-G16 -> 20430.88 | H17: =H14+H15-H16 -> 23924.38 | I17: =I14+I15-I16 -> 30105.83 | J17: =J14+J15-J16 -> 38428.142 | K17: =K14+K15-K16 -> 48418.408 | ... N17: =N14+N15-N16 -> 90525.607
B18: ERROR CHECK RESERVES | C18: =C17-'BALANCE SHEET'!C6 -> 0 | D18: =D17-'BALANCE SHEET'!D6 -> 0 | E18: =E17-'BALANCE SHEET'!E6 -> 0 | F18: =F17-'BALANCE SHEET'!F6 -> 0 | G18: =G17-'BALANCE SHEET'!G6 -> 0 | H18: =H17-'BALANCE SHEET'!H6 -> 0 | I18: =I17-'BALANCE SHEET'!I6 -> 0 | J18: =J17-'BALANCE SHEET'!J6 -> 0 | ... N18: =N17-'BALANCE SHEET'!N6 -> 0
B21: Dividend Payout Ratio | C21: ACTUAL | D21: ACTUAL | E21: ACTUAL | F21: ACTUAL | G21: ACTUAL | H21: ACTUAL | I21: ACTUAL | J21: FOCASTED | K21: FOCASTED | L21: FOCASTED | M21: FOCASTED | N21: FOCASTED
C22: 2019 | D22: 2020 | E22: 2021 | F22: 2022 | G22: 2023 | H22: 2024 | I22: 2025 | J22: 2026 | K22: 2027 | L22: 2028 | M22: 2029 | N22: 2030
B23: PAT | D23: ='INCOME STATEMENT'!D33 -> 1884.78 | E23: ='INCOME STATEMENT'!E33 -> 3574.42 | F23: ='INCOME STATEMENT'!F33 -> 5063.4 | G23: ='INCOME STATEMENT'!G33 -> 7355.1 | H23: ='INCOME STATEMENT'!H33 -> 8305.3 | I23: ='INCOME STATEMENT'!I33 -> 11221.84 | J23: ='INCOME STATEMENT'!J33 -> 13423.083 | K23: ='INCOME STATEMENT'!K33 -> 16113.333 | ... N23: ='INCOME STATEMENT'!N33 -> 26239.585
B24: Dividends | D24: ='CASH FLOW'!E25 -> 1051.05 | E24: ='CASH FLOW'!F25 -> 560.46 | F24: ='CASH FLOW'!G25 -> 1281.07 | G24: ='CASH FLOW'!H25 -> 2293 | H24: ='CASH FLOW'!I25 -> 4811.8 | I24: ='CASH FLOW'!J25 -> 5040.39 | J24: =J25*J23 -> 5100.7716 | K24: =K25*K23 -> 6123.0667 | L24: =L25*L23 -> 7276.4093 | M24: =M25*M23 -> 8560.1864 | N24: =N25*N23 -> 9971.0422 | P24: Payout ratio * PAT
B25: Payout Ratio | D25: =D24/D23 -> 0.55765129 | E25: =E24/E23 -> 0.15679747 | F25: =F24/F23 -> 0.25300589 | G25: =G24/G23 -> 0.31175647 | H25: =H24/H23 -> 0.57936498 | I25: =I24/I23 -> 0.44915896 | J25: =$P$25 -> 0.38 | K25: =$P$25 -> 0.38 | L25: =$P$25 -> 0.38 | M25: =$P$25 -> 0.38 | N25: =$P$25 -> 0.38 | P25: 0.38 | Q25: This assumption is based on the average of the company's historical dividend payout ratios from 2020 to 2025, which ranged from 16% to 58%. Using a historical average is a standard, data-driven practice for a base-case model, as it smooths out year-to-year volatility and avoids speculating on future dividend policy. This ensures the model is grounded in the company's past performance and provides a stable basis for the forecast.
B27: Other Non-current Liabilities Forcast | C27: ACTUAL | D27: ACTUAL | E27: ACTUAL | F27: ACTUAL | G27: ACTUAL | H27: ACTUAL | I27: ACTUAL | J27: FOCASTED | K27: FOCASTED | L27: FOCASTED | M27: FOCASTED | N27: FOCASTED
C28: 2019 | D28: 2020 | E28: 2021 | F28: 2022 | G28: 2023 | H28: 2024 | I28: 2025 | J28: 2026 | K28: 2027 | L28: 2028 | M28: 2029 | N28: 2030
B29: Other Non-current Liabilities | C29: ='BALANCE SHEET'!C9 -> 189.55 | D29: ='BALANCE SHEET'!D9 -> 263.09 | E29: ='BALANCE SHEET'!E9 -> 242.82 | F29: ='BALANCE SHEET'!F9 -> 469.61 | G29: ='BALANCE SHEET'!G9 -> 414.47 | H29: ='BALANCE SHEET'!H9 -> 552.36 | I29: ='BALANCE SHEET'!I9 -> 847.03 | J29: =I29*(1+I30) -> 1031.0648 | K29: =J29*(1+J30) -> 1397.0659 | L29: =K29*(1+K30) -> 1903.4806 | M29: =L29*(1+L30) -> 2493.2453 | N29: =M29*(1+M30) -> 3346.504 | P29: Forecasted Value=Previous Year′s Value×(1+3−Year Rolling CAGR)
B30: 3y CAGR | F30: =((F29/C29)^(1/3) -1) -> 0.35312479 | G30: =((G29/D29)^(1/3) -1) -> 0.16358001 | H30: =((H29/E29)^(1/3) -1) -> 0.31516201 | I30: =((I29/F29)^(1/3) -1) -> 0.21727065 | J30: =((J29/G29)^(1/3) -1) -> 0.35497396 | K30: =((K29/H29)^(1/3) -1) -> 0.36248446 | L30: =((L29/I29)^(1/3) -1) -> 0.30983488 | M30: =((M29/J29)^(1/3) -1) -> 0.34222818 | N30: =((N29/K29)^(1/3) -1) -> 0.33800629 | P30: 3−Year Rolling CAGR=(Value from 3 Years AgoCurrent Year′s Value​)^(1/3)​−1 | Q30: The forecast for Other Non-current Liabilities is based on a rolling 3-year Compound Annual Growth Rate (CAGR). This methodology was selected because the historical values showed a clear, albeit volatile, growth trend. Using a rolling CAGR allows the forecast to remain dynamic and reflect the most recent growth trends without being constrained by a single, static historical growth rate. This assumption implies that the company's non-current liabilities will continue to grow in line with its recent historical performance.
B32: Other current Liabilities Forcast | C32: ACTUAL | D32: ACTUAL | E32: ACTUAL | F32: ACTUAL | G32: ACTUAL | H32: ACTUAL | I32: ACTUAL | J32: FOCASTED | K32: FOCASTED | L32: FOCASTED | M32: FOCASTED | N32: FOCASTED
C33: 2019 | D33: 2020 | E33: 2021 | F33: 2022 | G33: 2023 | H33: 2024 | I33: 2025 | J33: 2026 | K33: 2027 | L33: 2028 | M33: 2029 | N33: 2030
B34: Total Liabilities | C34: ='BALANCE SHEET'!C14 -> 9132.44 | D34: ='BALANCE SHEET'!D14 -> 12121.57 | E34: ='BALANCE SHEET'!E14 -> 13776.76 | F34: ='BALANCE SHEET'!F14 -> 15933.49 | G34: ='BALANCE SHEET'!G14 -> 10800.16 | H34: ='BALANCE SHEET'!H14 -> 32579.67 | I34: ='BALANCE SHEET'!I14 -> 27037.8 | J34: ='BALANCE SHEET'!J14 -> 27287.851 | ... N34: ='BALANCE SHEET'!N14 -> 31077.876
B35: Other current Liabilities | C35: ='BALANCE SHEET'!C12 -> 8942.89 | D35: ='BALANCE SHEET'!D12 -> 11858.48 | E35: ='BALANCE SHEET'!E12 -> 13533.94 | F35: ='BALANCE SHEET'!F12 -> 15463.88 | G35: ='BALANCE SHEET'!G12 -> 10385.69 | H35: ='BALANCE SHEET'!H12 -> 32027.31 | I35: ='BALANCE SHEET'!I12 -> 26190.77 | J35: =I37*I34 -> 26256.786 | K35: =J37*J34 -> 26504.994 | L35: =K37*K34 -> 26793.579 | M35: =L37*L34 -> 27222.171 | N35: =M37*M34 -> 27731.371 | P35: Forecasted Value = Previous year avg * Previous total assets
B36: OCL as % of Total Assets | C36: =C35/C34 -> 0.97924432 | D36: =D35/D34 -> 0.97829572 | E36: =E35/E34 -> 0.98237467 | F36: =F35/F34 -> 0.97052686 | G36: =G35/G34 -> 0.96162372 | H36: =H35/H34 -> 0.98304587 | I36: =I35/I34 -> 0.96867238 | J36: =J35/J34 -> 0.96221524 | ... N36: =N35/N34 -> 0.89231876
B37: 3Y AVG | E37: =SUM(C36:E36)/3 -> 0.97997157 | F37: =SUM(D36:F36)/3 -> 0.97706575 | G37: =SUM(E36:G36)/3 -> 0.97150841 | H37: =SUM(F36:H36)/3 -> 0.97173215 | I37: =SUM(G36:I36)/3 -> 0.97111399 | J37: =SUM(H36:J36)/3 -> 0.97131116 | K37: =SUM(I36:K36)/3 -> 0.96027242 | L37: =SUM(J36:L36)/3 -> 0.94860491 | ... N37: =SUM(L36:N36)/3 -> 0.91402817 | P37: avg = (sum of Current 3 years%)/3 | Q37: The forecast for Other Current Liabilities is based on its historical relationship with Total Liabilities, a standard best practice in financial modeling. The forecast assumes Other Current Liabilities will remain a static percentage of Total Liabilities, derived from the average of the last three historical years' percentages. This approach provides a consistent and conservative growth assumption that normalizes the recent volatility and ensures a stable forecast.
B39: Settlement Gaurantee Fund (SGF) Forcast | C39: ACTUAL | D39: ACTUAL | E39: ACTUAL | F39: ACTUAL | G39: ACTUAL | H39: ACTUAL | I39: ACTUAL | J39: FOCASTED | K39: FOCASTED | L39: FOCASTED | M39: FOCASTED | N39: FOCASTED
C40: 2019 | D40: 2020 | E40: 2021 | F40: 2022 | G40: 2023 | H40: 2024 | I40: 2025 | J40: 2026 | K40: 2027 | L40: 2028 | M40: 2029 | N40: 2030
B41: Total Liabilities | C41: ='BALANCE SHEET'!C14 -> 9132.44 | D41: ='BALANCE SHEET'!D14 -> 12121.57 | E41: ='BALANCE SHEET'!E14 -> 13776.76 | F41: ='BALANCE SHEET'!F14 -> 15933.49 | G41: ='BALANCE SHEET'!G14 -> 10800.16 | H41: ='BALANCE SHEET'!H14 -> 32579.67 | I41: ='BALANCE SHEET'!I14 -> 27037.8 | J41: ='BALANCE SHEET'!J14 -> 27287.851 | ... N41: ='BALANCE SHEET'!N14 -> 31077.876
B42: Settlement Gaurantee Fund (SGF) | C42: ='BALANCE SHEET'!C16 -> 3057.68 | D42: ='BALANCE SHEET'!D16 -> 3426.77 | E42: ='BALANCE SHEET'!E16 -> 3792.93 | F42: ='BALANCE SHEET'!F16 -> 4255.23 | G42: ='BALANCE SHEET'!G16 -> 5283.8 | H42: ='BALANCE SHEET'!H16 -> 8910.45 | I42: ='BALANCE SHEET'!I16 -> 12075.51 | J42: =J44*J41 -> 11000.156 | K42: =K44*K41 -> 10446.797 | L42: =L44*L41 -> 11709.748 | M42: =M44*M41 -> 11743.256 | N42: =N44*N41 -> 12199.591 | P42: Forecasted Value = current year avg * total assets
B43: OCL as % of Total Assets | C43: =C42/C41 -> 0.33481523 | D43: =D42/D41 -> 0.28270018 | E43: =E42/E41 -> 0.27531364 | F43: =F42/F41 -> 0.26706202 | G43: =G42/G41 -> 0.48923349 | H43: =H42/H41 -> 0.27349725 | I43: =I42/I41 -> 0.44661585 | J43: =J42/J41 -> 0.40311553 | ... N43: =N42/N41 -> 0.39254907
B44: 3Y AVG | F44: =SUM(C43:E43)/3 -> 0.29760968 | G44: =SUM(D43:F43)/3 -> 0.27502528 | H44: =SUM(E43:G43)/3 -> 0.34386972 | I44: =SUM(F43:H43)/3 -> 0.34326425 | J44: =SUM(G43:I43)/3 -> 0.40311553 | K44: =SUM(H43:J43)/3 -> 0.37440954 | L44: =SUM(I43:K43)/3 -> 0.40804697 | M44: =SUM(J43:L43)/3 -> 0.39519068 | N44: =SUM(K43:M43)/3 -> 0.39254907 | P44: avg = (sum of previous 3 years%)/3 | Q44: The forecast for Settlement Guarantee Fund is based on its logical relationship with Total Liabilities. To account for the historical volatility of this line item, a 3-year rolling average is used as the forecasting assumption. This dynamic approach ensures the model's projections remain responsive to recent trends in the company's financial structure while adhering to financial modeling best practices by avoiding circular references.
B46: Other Non Current Assets Forcast | C46: ACTUAL | D46: ACTUAL | E46: ACTUAL | F46: ACTUAL | G46: ACTUAL | H46: ACTUAL | I46: ACTUAL | J46: FOCASTED | K46: FOCASTED | L46: FOCASTED | M46: FOCASTED | N46: FOCASTED
C47: 2019 | D47: 2020 | E47: 2021 | F47: 2022 | G47: 2023 | H47: 2024 | I47: 2025 | J47: 2026 | K47: 2027 | L47: 2028 | M47: 2029 | N47: 2030
B48: Fixed Assets | C48: ='BALANCE SHEET'!C20 -> 645.75 | D48: ='BALANCE SHEET'!D20 -> 631.81 | E48: ='BALANCE SHEET'!E20 -> 795.82 | F48: ='BALANCE SHEET'!F20 -> 1144.18 | G48: ='BALANCE SHEET'!G20 -> 1060.7 | H48: ='BALANCE SHEET'!H20 -> 1098.64 | I48: ='BALANCE SHEET'!I20 -> 1655.13 | J48: ='BALANCE SHEET'!J20 -> 2078.768 | ... N48: ='BALANCE SHEET'!N20 -> 4280.9952
B49: Other Non Current Assets | C49: ='BALANCE SHEET'!C21 -> 5958.6 | D49: ='BALANCE SHEET'!D21 -> 5372.7 | E49: ='BALANCE SHEET'!E21 -> 7984.79 | F49: ='BALANCE SHEET'!F21 -> 8074.19 | G49: ='BALANCE SHEET'!G21 -> 12538.66 | H49: ='BALANCE SHEET'!H21 -> 20970.17 | I49: ='BALANCE SHEET'!I21 -> 20588.79 | J49: =I52*I50 -> 20744.776 | K49: =J52*J50 -> 21185.798 | L49: =K52*K50 -> 21577.52 | M49: =L52*L50 -> 21997.037 | N49: =M52*M50 -> 22447.262 | P49: Forcasted Value = Previous Year TNCA * Previous year Avg
B50: Total Non-Current assets | C50: ='BALANCE SHEET'!C22 -> 6604.35 | D50: ='BALANCE SHEET'!D22 -> 6004.51 | E50: ='BALANCE SHEET'!E22 -> 8780.61 | F50: ='BALANCE SHEET'!F22 -> 9218.37 | G50: ='BALANCE SHEET'!G22 -> 13599.36 | H50: ='BALANCE SHEET'!H22 -> 22068.81 | I50: ='BALANCE SHEET'!I22 -> 22243.92 | J50: ='BALANCE SHEET'!J22 -> 22823.544 | ... N50: ='BALANCE SHEET'!N22 -> 26728.257
B51: ONCA as % of TNCA | C51: =C49/C50 -> 0.90222353 | D51: =D49/D50 -> 0.89477743 | E51: =E49/E50 -> 0.90936621 | F51: =F49/F50 -> 0.87588044 | G51: =G49/G50 -> 0.92200368 | H51: =H49/H50 -> 0.95021752 | I51: =I49/I50 -> 0.9255918 | J51: =J49/J50 -> 0.90892002 | ... N51: =N49/N50 -> 0.83983261
B52: 3Y AVG | E52: =SUM(C51:E51)/3 -> 0.90212239 | F52: =SUM(D51:F51)/3 -> 0.89334136 | G52: =SUM(E51:G51)/3 -> 0.90241678 | H52: =SUM(F51:H51)/3 -> 0.91603388 | I52: =SUM(G51:I51)/3 -> 0.93260434 | J52: =SUM(H51:J51)/3 -> 0.92824311 | K52: =SUM(I51:K51)/3 -> 0.9090048 | L52: =SUM(J51:L51)/3 -> 0.89220344 | ... N52: =SUM(L51:N51)/3 -> 0.85751287 | P52: avg = (sum of recent 3y %) / 3 | Q52: The forecast for Other Non-Current Assets is based on its historical relationship with Total Non-Current Assets. Given the line item's nature as a component of the total, the most logical and auditable approach is to project it as a percentage of Total Non-Current Assets. The forecasting assumption is derived from the average of the last three historical percentages, which captures the most recent trends.
B54: Trade Receivables Forcast [DSO Method] | C54: ACTUAL | D54: ACTUAL | E54: ACTUAL | F54: ACTUAL | G54: ACTUAL | H54: ACTUAL | I54: ACTUAL | J54: FOCASTED | K54: FOCASTED | L54: FOCASTED | M54: FOCASTED | N54: FOCASTED
C55: 2019 | D55: 2020 | E55: 2021 | F55: 2022 | G55: 2023 | H55: 2024 | I55: 2025 | J55: 2026 | K55: 2027 | L55: 2028 | M55: 2029 | N55: 2030
B56: Trade Receivables | C56: ='BALANCE SHEET'!C24 -> 452.51 | D56: ='BALANCE SHEET'!D24 -> 652.11 | E56: ='BALANCE SHEET'!E24 -> 998.58 | F56: ='BALANCE SHEET'!F24 -> 1614.95 | G56: ='BALANCE SHEET'!G24 -> 1589.21 | H56: ='BALANCE SHEET'!H24 -> 1864.66 | I56: ='BALANCE SHEET'!I24 -> 1512.21 | J56: =J57*I59/365 -> 2386.5907 | K56: =K57*J59/365 -> 2716.1676 | L56: =L57*K59/365 -> 3044.8238 | M56: =M57*L59/365 -> 3733.9155 | N56: =N57*M59/365 -> 4186.6528 | P56: Forcasted Value = [Current Year Revenue * Previous Year Avg dso] / 365 | Q56: The forecast for Trade Receivables is based on the Days Sales Outstanding (DSO) method, which links receivables to the company's revenue and collection period. To capture recent trends and provide a more dynamic forecast, the DSO assumption is not held static. Instead, it is based on a 3-year rolling average of the company's historical DSO. This approach allows the forecast to evolve with the company's revenue and collection efficiency.
B57: Revenue | C57: ='INCOME STATEMENT'!C4 -> 2997.42 | D57: ='INCOME STATEMENT'!D4 -> 3507.93 | E57: ='INCOME STATEMENT'!E4 -> 5624.82 | F57: ='INCOME STATEMENT'!F4 -> 8929 | G57: ='INCOME STATEMENT'!G4 -> 11856 | H57: ='INCOME STATEMENT'!H4 -> 14780 | I57: ='INCOME STATEMENT'!I4 -> 17141 | J57: ='INCOME STATEMENT'!J4 -> 20740.61 | ... N57: ='INCOME STATEMENT'!N4 -> 39182.776
B58: DSO | C58: =ROUND(C56*365/C57,0) -> 55 | D58: =ROUND(D56*365/D57,0) -> 68 | E58: =ROUND(E56*365/E57,0) -> 65 | F58: =ROUND(F56*365/F57,0) -> 66 | G58: =ROUND(G56*365/G57,0) -> 49 | H58: =ROUND(H56*365/H57,0) -> 46 | I58: =ROUND(I56*365/I57,0) -> 32 | J58: =ROUND(J56*365/J57,0) -> 42 | ... N58: =ROUND(N56*365/N57,0) -> 39 | P58: DSO = [ Trade Receivables*365] / Revenue
B59: 3Y AVG DSO | E59: =ROUND(AVERAGE(C58:E58),0) -> 63 | F59: =ROUND(AVERAGE(D58:F58),0) -> 66 | G59: =ROUND(AVERAGE(E58:G58),0) -> 60 | H59: =ROUND(AVERAGE(F58:H58),0) -> 54 | I59: =ROUND(AVERAGE(G58:I58),0) -> 42 | J59: =ROUND(AVERAGE(H58:J58),0) -> 40 | K59: =ROUND(AVERAGE(I58:K58),0) -> 38 | L59: =ROUND(AVERAGE(J58:L58),0) -> 40 | ... N59: =ROUND(AVERAGE(L58:N58),0) -> 39 | P59: 3Y AVG DSO = (sum of recent 3y DSO) / 3
B61: Other Non Current Assets Forcast | C61: ACTUAL | D61: ACTUAL | E61: ACTUAL | F61: ACTUAL | G61: ACTUAL | H61: ACTUAL | I61: ACTUAL | J61: FOCASTED | K61: FOCASTED | L61: FOCASTED | M61: FOCASTED | N61: FOCASTED
C62: 2019 | D62: 2020 | E62: 2021 | F62: 2022 | G62: 2023 | H62: 2024 | I62: 2025 | J62: 2026 | K62: 2027 | L62: 2028 | M62: 2029 | N62: 2030
B63: Revenue | C63: ='INCOME STATEMENT'!C4 -> 2997.42 | D63: ='INCOME STATEMENT'!D4 -> 3507.93 | E63: ='INCOME STATEMENT'!E4 -> 5624.82 | F63: ='INCOME STATEMENT'!F4 -> 8929 | G63: ='INCOME STATEMENT'!G4 -> 11856 | H63: ='INCOME STATEMENT'!H4 -> 14780 | I63: ='INCOME STATEMENT'!I4 -> 17141 | J63: ='INCOME STATEMENT'!J4 -> 20740.61 | ... N63: ='INCOME STATEMENT'!N4 -> 39182.776
B64: Other Current assets | C64: ='BALANCE SHEET'!C26 -> 3380.84 | D64: ='BALANCE SHEET'!D26 -> 7835.81 | E64: ='BALANCE SHEET'!E26 -> 5968.9 | F64: ='BALANCE SHEET'!F26 -> 8450.94 | G64: ='BALANCE SHEET'!G26 -> 9006.38 | H64: ='BALANCE SHEET'!H26 -> 11566.99 | I64: ='BALANCE SHEET'!I26 -> 17957.9 | J64: =J63*I66 -> 17905.48 | K64: =K63*J66 -> 22253.436 | L64: =L63*K66 -> 27382.573 | M64: =M63*L66 -> 30635.673 | N64: =N63*M66 -> 35699.131 | P64: Forcasted Value = [Current Year Revenue * Previous Year Avg ] | Q64: The forecast for Other Current Assets is driven by a strong correlation to Revenue. To account for the historical volatility in this relationship, likely due to external factors, the forecasting assumption is based on a 3-year rolling average of Other Current Assets as a percentage of Revenue. This methodology smooths out short-term fluctuations and bases the forecast on the company's most recent operational trend.
B65: OCA as % of Revenue | C65: =C64/C63 -> 1.1279167 | D65: =D64/D63 -> 2.2337418 | E65: =E64/E63 -> 1.0611717 | F65: =F64/F63 -> 0.94645985 | G65: =G64/G63 -> 0.75964744 | H65: =H64/H63 -> 0.78261096 | I65: =I64/I63 -> 1.0476577 | J65: =J64/J63 -> 0.86330535 | ... N65: =N64/N63 -> 0.91109244
B66: rolling 3y AVG | E66: =SUM(C65:E65)/3 -> 1.4742767 | F66: =SUM(D65:F65)/3 -> 1.4137911 | G66: =SUM(E65:G65)/3 -> 0.92242634 | H66: =SUM(F65:H65)/3 -> 0.82957275 | I66: =SUM(G65:I65)/3 -> 0.86330535 | J66: =SUM(H65:J65)/3 -> 0.89785799 | K66: =SUM(I65:K65)/3 -> 0.93627367 | L66: =SUM(J65:L65)/3 -> 0.89914567 | ... N66: =SUM(L65:N65)/3 -> 0.91550393 | P66: avg = (sum of recent 3y %) / 3
B68: Other Non Current Assets Forcast | C68: ACTUAL | D68: ACTUAL | E68: ACTUAL | F68: ACTUAL | G68: ACTUAL | H68: ACTUAL | I68: ACTUAL | J68: FOCASTED | K68: FOCASTED | L68: FOCASTED | M68: FOCASTED | N68: FOCASTED
C69: 2019 | D69: 2020 | E69: 2021 | F69: 2022 | G69: 2023 | H69: 2024 | I69: 2025 | J69: 2026 | K69: 2027 | L69: 2028 | M69: 2029 | N69: 2030
B70: Change in Trade Receivables | D70: ='CASH FLOW'!E8 -> -199.6 | E70: ='CASH FLOW'!F8 -> -346.47 | F70: ='CASH FLOW'!G8 -> -616.37 | G70: ='CASH FLOW'!H8 -> 25.74 | H70: ='CASH FLOW'!I8 -> -275.45 | I70: ='CASH FLOW'!J8 -> 352.45 | J70: ='CASH FLOW'!K8 -> -874.38074 | K70: ='CASH FLOW'!L8 -> -329.57682 | ... N70: ='CASH FLOW'!O8 -> -452.73726
B71: Change in Other Current Assets | D71: ='CASH FLOW'!E9 -> -4454.97 | E71: ='CASH FLOW'!F9 -> 1866.91 | F71: ='CASH FLOW'!G9 -> -2482.04 | G71: ='CASH FLOW'!H9 -> -555.44 | H71: ='CASH FLOW'!I9 -> -2560.61 | I71: ='CASH FLOW'!J9 -> -6390.91 | J71: ='CASH FLOW'!K9 -> 52.420359 | K71: ='CASH FLOW'!L9 -> -4347.9567 | ... N71: ='CASH FLOW'!O9 -> -5063.4586
B72: Change in Other Current Liabilities | D72: ='CASH FLOW'!E10 -> 2915.59 | E72: ='CASH FLOW'!F10 -> 1675.46 | F72: ='CASH FLOW'!G10 -> 1929.94 | G72: ='CASH FLOW'!H10 -> -5078.19 | H72: ='CASH FLOW'!I10 -> 21641.62 | I72: ='CASH FLOW'!J10 -> -5836.54 | J72: ='CASH FLOW'!K10 -> 66.015773 | K72: ='CASH FLOW'!L10 -> 248.20808 | ... N72: ='CASH FLOW'!O10 -> 509.20028
B73: Total Change in Net Working Capital | D73: =SUM(D70:D72) -> -1738.98 | E73: =SUM(E70:E72) -> 3195.9 | F73: =SUM(F70:F72) -> -1168.47 | G73: =SUM(G70:G72) -> -5607.89 | H73: =SUM(H70:H72) -> 18805.56 | I73: =SUM(I70:I72) -> -11875 | J73: =SUM(J70:J72) -> -755.94461 | K73: =SUM(K70:K72) -> -4429.3254 | ... N73: =SUM(N70:N72) -> -5006.9956 | P73: Total Change in Net Working Capital = sum of all changes

Sheet BETA AND EV_MULTIPLE CALCULATIO
I1: REASONING FOR ASSUMPTION
B2: BETA CALCULATION
B3: Company | C3: Ticker | D3: Levered Beta | E3: D/E Ratio | F3: Corporate Tax Rate | G3: Unlevered Beta
B4: B.S.E Ltd. | C4: BSE | D4: 0.11 | E4: 0 | F4: 0.25 | G4: 0.11
B5: Multi commodity Exchange | C5: MCX | D5: 0.38 | E5: 0 | F5: 0.25 | G5: 0.38
B6: Central Depository Services | C6: CDSL | D6: 0.19 | E6: 0 | F6: 0.25 | G6: 0.19
B7: Average Unlevered Beta | G7: =AVERAGE(G4:G6) -> 0.22666667 | I7: The Beta of 0.23 was derived from a comparable company analysis of BSE, MCX, and CDSL. As the target company is privately held, this methodology provides a reliable estimate of its business risk. These specific companies were chosen as they are publicly traded exchanges or financial market infrastructure companies in India and therefore share similar operational, regulatory, and economic risks with the target company.
I8: The analysis was based on the levered betas of the comparable companies, with the Debt-to-Equity (D/E) ratio used to remove financial risk. It was noted that all three companies are all-equity financed, with a D/E ratio of zero, meaning their unlevered beta is equal to their levered beta. A consistent corporate tax rate of 25% was used in the unlevering formula, aligning with income statement projections. The average unlevered beta of 0.23 reflects a conservative and defensible measure of the target company's underlying business risk.
B11: Company | C11: Ticker | D11: Enterprise Value | E11: EBITDA | F11: EV/EBITDA Multiple
B12: B.S.E Ltd. | C12: BSE | D12: 85818 | E12: 2638 | F12: =D12/E12 -> 32.531463 | I12: The Enterprise Value (EV) and LTM EBITDA values for the three comparable companies were sourced from public financial data to conduct a Comparable Company Analysis (CCA). This analysis provides a market-based valuation that serves as a sanity check for the DCF model. For each comparable company, the EV/EBITDA multiple was calculated by dividing its Enterprise Value by its LTM EBITDA. This multiple is a standard valuation metric because both EV and EBITDA are capital structure-neutral. The median of these multiples was then selected as the most representative and defensible Exit Multiple for the valuation.
B13: Multi commodity Exchange | C13: MCX | D13: 39518 | E13: 892 | F13: =D13/E13 -> 44.302691
B14: Central Depository Services | C14: CDSL | D14: 32108 | E14: 699 | F14: =D14/E14 -> 45.934192
B15: Median Multiple | F15: =MEDIAN(F12:F14) -> 44.302691 | I15: The median multiple is used because it provides a more reliable and representative estimate than the average. It is a professional best practice to use the median as it filters out the impact of any outliers in the data, which could otherwise skew the result and lead to a less defensible valuation. This ensures that the Exit Multiple is a conservative and realistic reflection of the peer group's typical valuation. We will use this median to finalize the Exit Multiple Terminal Value.

Sheet Free Cash Flow Calculation.
B2: YEAR | C2: ACTUAL | D2: ACTUAL | E2: ACTUAL | F2: ACTUAL | G2: ACTUAL | H2: ACTUAL | I2: ACTUAL | J2: FOCASTED | K2: FOCASTED | L2: FOCASTED | M2: FOCASTED | N2: FOCASTED | P2: ASSUMED VALUES | Q2: REASONING FOR ASSUMPTION
C3: 2019 | D3: 2020 | E3: 2021 | F3: 2022 | G3: 2023 | H3: 2024 | I3: 2025 | J3: 2026 | K3: 2027 | L3: 2028 | M3: 2029 | N3: 2030
B4: Net Income | C4: ='INCOME STATEMENT'!C33 -> 1708.04 | D4: ='INCOME STATEMENT'!D33 -> 1884.78 | E4: ='INCOME STATEMENT'!E33 -> 3574.42 | F4: ='INCOME STATEMENT'!F33 -> 5063.4 | G4: ='INCOME STATEMENT'!G33 -> 7355.1 | H4: ='INCOME STATEMENT'!H33 -> 8305.3 | I4: ='INCOME STATEMENT'!I33 -> 11221.84 | J4: ='INCOME STATEMENT'!J33 -> 13423.083 | ... N4: ='INCOME STATEMENT'!N33 -> 26239.585
B5: D&A | C5: ='INCOME STATEMENT'!C19 -> 142.02 | D5: ='INCOME STATEMENT'!D19 -> 180.78 | E5: ='INCOME STATEMENT'!E19 -> 226.01 | F5: ='INCOME STATEMENT'!F19 -> 338 | G5: ='INCOME STATEMENT'!G19 -> 384 | H5: ='INCOME STATEMENT'!H19 -> 439 | I5: ='INCOME STATEMENT'!I19 -> 546.59 | J5: ='INCOME STATEMENT'!J19 -> 737.83614 | ... N5: ='INCOME STATEMENT'!N19 -> 1568.1785
B6: Total Change in Net Working Capital | D6: ='FORCAST SCHEDULES'!D73 -> -1738.98 | E6: ='FORCAST SCHEDULES'!E73 -> 3195.9 | F6: ='FORCAST SCHEDULES'!F73 -> -1168.47 | G6: ='FORCAST SCHEDULES'!G73 -> -5607.89 | H6: ='FORCAST SCHEDULES'!H73 -> 18805.56 | I6: ='FORCAST SCHEDULES'!I73 -> -11875 | J6: ='FORCAST SCHEDULES'!J73 -> -755.94461 | K6: ='FORCAST SCHEDULES'!K73 -> -4429.3254 | ... N6: ='FORCAST SCHEDULES'!N73 -> -5006.9956
B7: Capex | D7: ='CASH FLOW'!E16 -> 166.84 | E7: ='CASH FLOW'!F16 -> 390.02 | F7: ='CASH FLOW'!G16 -> 686.36 | G7: ='CASH FLOW'!H16 -> 300.52 | H7: ='CASH FLOW'!I16 -> 476.94 | I7: ='CASH FLOW'!J16 -> 1103.08 | J7: ='CASH FLOW'!K16 -> 1161.4742 | K7: ='CASH FLOW'!L16 -> 1387.9616 | ... N7: ='CASH FLOW'!O16 -> 2194.2355
B8: FCFF / FCFE | D8: =D4+D5-D6-D7 -> 3637.7 | E8: =E4+E5-E6-E7 -> 214.51 | F8: =F4+F5-F6-F7 -> 5883.51 | G8: =G4+G5-G6-G7 -> 13046.47 | H8: =H4+H5-H6-H7 -> -10538.2 | I8: =I4+I5-I6-I7 -> 22540.35 | J8: =J4+J5-J6-J7 -> 13755.39 | K8: =K4+K5-K6-K7 -> 20069.704 | ... N8: =N4+N5-N6-N7 -> 30620.523 | P8: FCFF = Net Income + D&A - Change in Net Working Capital - Capex | Q8: Free Cash Flow to Firm (FCFF) represents the cash flow available to all capital providers of the NSE—both its debt and equity holders—before any debt payments are made. Free Cash Flow to Equity (FCFE), on the other hand, is the cash flow available only to the NSE's equity holders after all debt obligations have been met. The key distinction between these two metrics is the presence of debt. Since the NSE is a debt-free company, there is no interest expense to subtract or net change in borrowings to add, which simplifies the FCFE formula, making it equal to the FCFF. This is why for the NSE, FCFF and FCFE are the same.

Sheet WACC AND DCF CALCULATION
B2: WACC CALCULATION
B3: Cost of Equity Componenets | C3: values | K3: REASONING FOR ASSUMPTION
B4: Risk-free Rate (Rf) | C4: 0.0649 | K4: The reasoning for using 6.49% as the risk-free rate for this valuation is that it is the most credible and defensible proxy available. This value, as of September 16, 2025, is the yield on the India 10-year Government Bond. We use this specific benchmark because it is issued by the sovereign government, implying it has virtually no risk of default, and its 10-year maturity aligns appropriately with the long-term nature of our DCF analysis. By anchoring our model to this objective and transparent data point, we ensure our WACC calculation is built on sound financial principles and can be easily verified.
B5: Market Risk Premium (MRP) | C5: 0.0515 | K5: "The Market Risk Premium (MRP) of 5.15% is based on the historical methodology. This value is derived by calculating the difference between the long-term annualized return of the Indian market and its corresponding long-term average risk-free rate. The annualized return of the Nifty 50 over its 29-year history is approximately 11.64%, while the long-term average 10-year Indian Government Bond yield is assumed to be 6.49%. This method is a data-driven approach that provides a robust, transparent, and defensible benchmark for the premium required by investors for assuming market risk."
B6: Beta (β) | C6: ='BETA AND EV_MULTIPLE CALCULATIO'!G7 -> 0.22666667 | K6: The Beta of 0.23 was derived from a comparable company analysis of BSE, MCX, and CDSL. As the target company is privately held, this methodology provides a reliable estimate of its business risk. These companies were selected because they are publicly traded exchanges or financial market infrastructure companies in India and therefore share similar operational, regulatory, and economic risks with the target company. The analysis was based on the levered betas of the comparable companies, with the Debt-to-Equity (D/E) ratio used to remove financial risk. It was noted that all three companies are all-equity financed, with a D/E ratio of zero, meaning their unlevered beta is equal to their levered beta. A consistent corporate tax rate of 25% was used in the unlevering formula, aligning with income statement projections. The average unlevered beta of 0.23 reflects a conservative and defensible measure of the target company's underlying business risk.
B7: Cost of Equity (Re) | C7: =C4+C6*C5 -> 0.076573333 | K7: The Cost of Equity was determined to be 7.67%. This was calculated using the Capital Asset Pricing Model (CAPM), where Re​=Rf​+β×(Rm​−Rf​). The calculation factors in a Risk-Free Rate of 6.49%, a Market Risk Premium of 5.15%, and a Beta of 0.23. This figure represents the return required by the company's equity investors and will be used in the final WACC calculation.
B9: Cost of Debt Componenets | C9: values | K9: REASONING FOR ASSUMPTION
B10: Pre-Tax Cost of Debt (Rd​) | C10: 0 | K10: The Cost of Debt was determined to be 0%. This assumption is based on the company's capital structure, as it has no outstanding interest-bearing debt. Since there are no interest expenses, the pre-tax cost of debt is 0%, and due to the tax shield, the after-tax cost is also 0%. This is a defensible assumption, consistent with the company's historical and projected all-equity financing.
B11: Corporate Tax Rate | C11: 0.25 | K11: The 25% corporate tax rate is consistent with the rate used in the income statement projections.
B12: After-Tax Cost of Debt | C12: 0 | K12: The Cost of Debt was determined to be 0%. This assumption is based on the company's capital structure, as it has no outstanding interest-bearing debt. Since there are no interest expenses, the pre-tax cost of debt is 0%. The after-tax cost of debt, calculated as Pre-Tax Cost of Debt×(1−Corporate Tax Rate), is also 0%. This is a defensible assumption, consistent with the company's historical and projected all-equity financing.
B14: Capital Stucture | C14: values | K14: REASONING FOR ASSUMPTION
B15: Market Value of Equity (E) | C15: ='BALANCE SHEET'!I7 -> 30353.33 | K15: The Market Value of Equity was determined to be Rs 30,353.33 crore. Since the company is privately held, its market value is not publicly available. Therefore, the Total Equity from the company's most recent fiscal year-end balance sheet was used as a defensible proxy for its market value.
B16: Market Value of Debt (D) | C16: 0 | K16: The Market Value of Debt was determined to be Rs 0. This is a key assumption based on the company's all-equity financing structure. Since the company has no outstanding interest-bearing debt, its total debt value is zero.
B17: Total Capital (V) | C17: =C15+C16 -> 30353.33 | K17: The Total Capital of the firm was determined to be Rs 30,353.33 crore. This value is the sum of the company's Market Value of Equity (Rs 30,353.33 crore) and its Market Value of Debt (Rs 0). This figure represents the total value of the company's capital structure and is the denominator for the weighting in the final WACC calculation.
B18: % Equity (E/V) | C18: =C15/C17 -> 1 | K18: The company's capital structure weights are 100% Equity and 0% Debt. This is a direct result of the company's all-equity financing, where the Market Value of Debt is zero. This assumption is consistent with the company's historical financing strategy and the inputs used in this valuation.
B19: % Debt (D/V) | C19: =C16/C17 -> 0
B21: WACC | C21: values
B22: WACC | C22: =C18*C7 -> 0.076573333 | K22: The Weighted Average Cost of Capital (WACC) was determined to be 7.67%. This figure represents the blended cost of both equity and debt capital, weighted by the company's long-term capital structure. The WACC was calculated using the formula WACC=(VE​×Re​)+(VD​×Rd​×(1−T)). The Cost of Equity was derived from a Beta of 0.23, which was based on a comparable company analysis, while the Cost of Debt was determined to be 0% due to the company's all-equity capital structure. The WACC of 7.67% is a defensible discount rate to be used in a Discounted Cash Flow (DCF) model, as it accurately reflects the company's specific business risk and capital structure
B25: Unlevered Free Cash Flow (UFCF)
C26: FOCASTED | D26: FOCASTED | E26: FOCASTED | F26: FOCASTED | G26: FOCASTED | K26: REASONING FOR ASSUMPTION
B27: YEAR | C27: 2026 | D27: 2027 | E27: 2028 | F27: 2029 | G27: 2030
B28: EBIT | C28: ='INCOME STATEMENT'!J20 -> 15205.471 | D28: ='INCOME STATEMENT'!K20 -> 18137.245 | E28: ='INCOME STATEMENT'!L20 -> 21369.353 | F28: ='INCOME STATEMENT'!M20 -> 24860.825 | G28: ='INCOME STATEMENT'!N20 -> 28551.622 | K28: Reasoning: The EBIT and Tax Rate are taken directly from your forecasted income statement. EBIT is the ideal starting point because it isolates the company's operating performance, removing the effects of financing (interest) and taxes. The tax rate is applied to this figure to arrive at the hypothetical operating profit after taxes.
B29: Tax Rate | C29: ='INCOME STATEMENT'!J30 -> 0.25 | D29: ='INCOME STATEMENT'!K30 -> 0.25 | E29: ='INCOME STATEMENT'!L30 -> 0.25 | F29: ='INCOME STATEMENT'!M30 -> 0.25 | G29: ='INCOME STATEMENT'!N30 -> 0.25
B30: Taxes | C30: =C28*C29 -> 3801.3677 | D30: =D28*D29 -> 4534.3112 | E30: =E28*E29 -> 5342.3381 | F30: =F28*F29 -> 6215.2063 | G30: =G28*G29 -> 7137.9054 | K30: EBIT*TAX RATE
B31: NOPAT | C31: =C28-C30 -> 11404.103 | D31: =D28-D30 -> 13602.933 | E31: =E28-E30 -> 16027.014 | F31: =F28-F30 -> 18645.619 | G31: =G28-G30 -> 21413.716 | K31: NOPAT is the final figure for a company's operational profitability after taxes. It is a critical line item because it represents the earnings generated from the core business, on a post-tax basis, without the influence of the company's debt or financing decisions. The formula for this is: NOPAT = EBIT × (1 - Tax Rate)
B32: D&A | C32: ='INCOME STATEMENT'!J19 -> 737.83614 | D32: ='INCOME STATEMENT'!K19 -> 915.00712 | E32: ='INCOME STATEMENT'!L19 -> 1112.3046 | F32: ='INCOME STATEMENT'!M19 -> 1330.3053 | G32: ='INCOME STATEMENT'!N19 -> 1568.1785 | K32: D&A are non-cash expenses. They are subtracted from a company's revenue to calculate net income for accounting purposes, but they do not represent an actual outflow of cash in the current period. Therefore, we add them back to NOPAT to reflect the true cash available to the business.
B33: CapEx | C33: ='FORCAST SCHEDULES'!J5 -> 1161.4742 | D33: ='FORCAST SCHEDULES'!K5 -> 1387.9616 | E33: ='FORCAST SCHEDULES'!L5 -> 1637.7947 | F33: ='FORCAST SCHEDULES'!M5 -> 1908.0308 | G33: ='FORCAST SCHEDULES'!N5 -> 2194.2355 | K33: CapEx is a real cash outflow. It is the money a company must spend on long-term assets, like property, plant, and equipment, to maintain and grow its operations. Since it is a necessary investment for the business to continue generating future cash flows, we subtract it from the calculation.
B34: Change in NWC | C34: ='FORCAST SCHEDULES'!J73 -> -755.94461 | D34: ='FORCAST SCHEDULES'!K73 -> -4429.3254 | E34: ='FORCAST SCHEDULES'!L73 -> -5169.2078 | F34: ='FORCAST SCHEDULES'!M73 -> -3513.5992 | G34: ='FORCAST SCHEDULES'!N73 -> -5006.9956 | K34: This line item adjusts for the cash that is either tied up or freed from a company's short-term operations. A positive change in NWC (e.g., an increase in inventory) is a cash outflow and is subtracted, whereas a negative change (e.g., collecting cash from customers faster) is a cash inflow and is effectively added back to cash flow.
B35: Unlevered Free Cash Flow (UFCF) | C35: =C31+C32-C33-C34 -> 11736.41 | D35: =D31+D32-D33-D34 -> 17559.304 | E35: =E31+E32-E33-E34 -> 20670.732 | F35: =F31+F32-F33-F34 -> 21581.492 | G35: =G31+G32-G33-G34 -> 25794.655 | K35: UFCF = NOPAT + D&A - CapEx - Change in NWC
B38: Perpetuity Growth Terminal Value Calculation | K38: REASONING FOR ASSUMPTION
B39: Term | C39: Input | D39: Formula
B40: UFCF (2030) | C40: =G35 -> 25794.655 | D40: Terminal Value = [UFCF_last_year * (1 + g)] / (WACC - g)
B41: Perpentual Growth Rate(g) | C41: 0.06
B42: WACC | C42: =C22 -> 0.076573333 | K42: The 6% perpetuity growth rate (g) is a realistic and defensible assumption. This rate aligns with the estimated long-term nominal GDP growth rate of the Indian economy, reflecting the country's status as a fast-growing, developing market. The assumption is also mathematically sound, as the 6% growth rate is less than the company's WACC of 7.66%, ensuring a finite and meaningful Terminal Value.
B43: Terminal Value | C43: =(C40*(1+C41))/(C42-C41) -> 1649778.8 | K43: The Terminal Value represents the cash flows beyond our explicit forecast period. It is a single value that captures the long-term, sustainable growth of the business into perpetuity. The value is highly sensitive to the perpetuity growth rate (g) and the WACC, and it often accounts for a significant portion of the total valuation.
B46: Exit Multiple Terminal Value Calculation | K46: REASONING FOR ASSUMPTION
B47: Term | C47: Input | D47: Formula
B48: EBITDA (2030) | C48: ='INCOME STATEMENT'!N15 -> 30119.8 | D48: Terminal Value = EBITDA (Final Year) x Exit Multiple
B49: Exit Multiple | C49: ='BETA AND EV_MULTIPLE CALCULATIO'!F15 -> 44.302691 | K49: FROM COMPARABLE COMPANY ANALYSIS
B50: Terminal Value | C50: =C48*C49 -> 1334388.2
B53: Present Value of Cash Flows
B54: YEAR | C54: FOCASTED | D54: FOCASTED | E54: FOCASTED | F54: FOCASTED | G54: FOCASTED | H54: Total | I54: Formula
C55: 2026 | D55: 2027 | E55: 2028 | F55: 2029 | G55: 2030
B56: UFCF | C56: =C35 -> 11736.41 | D56: =D35 -> 17559.304 | E56: =E35 -> 20670.732 | F56: =F35 -> 21581.492 | G56: =G35 -> 25794.655
B57: Discount Factor | C57: =1/(1+$C$22)^1 -> 0.92887309 | D57: =1/(1+$C$22)^2 -> 0.86280522 | E57: =1/(1+$C$22)^3 -> 0.80143655 | F57: =1/(1+$C$22)^4 -> 0.74443285 | G57: =1/(1+$C$22)^5 -> 0.69148364 | I57: Discount Factor = 1 / (1 + WACC)^n
B58: Present Value | C58: =C56*C57 -> 10901.635 | D58: =D56*D57 -> 15150.259 | E58: =E56*E57 -> 16566.28 | F58: =F56*F57 -> 16065.972 | G58: =G56*G57 -> 17836.582 | H58: =SUM(C58:G58) -> 76520.729 | I58: Present Value = UFCF / (1 + wacc)^n
B59: PV of TV (Perpetuity) | G59: =C43*G57 -> 1140795.1 | I59: PV of TV = Terminal Value / (1 + WACC)^n | K59: The Terminal Value, which accounts for the majority of the total Enterprise Value, is based on two defensible methods. The Perpetuity Growth Method uses a realistic long-term growth rate (g) assumption, while the Exit Multiple Method is based on the median EV/EBITDA multiple of a comparable peer group. Using the median is a professional standard that minimizes the impact of outliers and provides a market-based validation of the intrinsic valuation.
B60: PV of TV (Exit Multiple) | G60: =C50*G57 -> 922707.6 | I60: PV of TV = Terminal Value / (1 + WACC)^n | K60: The final Enterprise Value is presented as a range based on these two methods. This approach provides a more robust and defensible valuation than relying on a single number, reflecting a comprehensive analysis of both the company's intrinsic value and its relative market position.
B61: Total Enterprise Value | H61: =G59+H58 -> 1217315.8
B62: (Perpetuity Growth) | H62: =G60+H58 -> 999228.33
B65: Perpetuity Growth Case | E65: Exit Multiple Case:
B66: Enterprise Value: | C66: =H61 -> 1217315.8 | E66: Enterprise Value: | F66: =H62 -> 999228.33
B67: Less: Net Debt: | C67: 0 | E67: Less: Net Debt: | F67: 0
B68: Plus: Minority Interest: | C68: 0 | E68: Plus: Minority Interest: | F68: 0
B69: Equals: Equity Value: | C69: =C66-C67+C68 -> 1217315.8 | E69: Equals: Equity Value: | F69: =F66-F67+F68 -> 999228.33
B71: Equity Value for Perpetuity Growth Case | E71: Equity Value for Exit Multiple Case:
B72: Equity Value | C72: =C69 -> 1217315.8 | E72: Equity Value | F72: =F69 -> 999228.33
B73: Diluted Shares Outstanding | C73: ='INCOME STATEMENT'!J38 -> 247.5 | E73: Diluted Shares Outstanding | F73: =C73 -> 247.5
B74: Equals: Equity Value: | C74: =C72/C73 -> 4918.4476 | E74: Equals: Equity Value: | F74: =F72/F73 -> 4037.2862
B80: SENSITIVITY ANALYSIS | J80: REASONING FOR ASSUMPTION
D81: wacc | J81: The ranges used in your sensitivity analysis are based on financial modeling best practices, not arbitrary choices. They are designed to test the two most critical assumptions in a DCF model. For the WACC, your range of 6.66% to 8.66% tests the company's valuation under different risk scenarios, with a lower WACC assuming less risk and a higher WACC assuming more. It is a standard practice to test a range around your calculated base case. For the perpetual growth rate, your range of 4% to 8% tests the company's valuation against different long-term growth scenarios. A company's long-term growth rate cannot exceed the growth of its underlying economy forever, so your base case of 6% is quite optimistic. The lower bound of your range (4%) is a more conservative, realistic assumption for long-term growth. By showing how your valuation changes across all these scenarios, you are demonstrating the sensitivity of your model and the inherent risk in your assumptions. This provides a professional and credible view of the company's true value, proving that it is not a single number but a range of possible outcomes.
C82: =H61 -> 1217315.8 | D82: =E82-0.005 -> 0.0666 | E82: =F82-0.005 -> 0.0716 | F82: 0.0766 | G82: =F82+0.005 -> 0.0816 | H82: =G82+0.005 -> 0.0866
B83: Perpetual Growth Rate(g) | C83: 0.04 | D83: 809425.1 | E83: 678437.93 | F83: 583283.74 | G83: 511041.06 | H83: 454334.12
C84: 0.05 | D84: 1260796.1 | E84: 965025.97 | F84: 780503.08 | G84: 654419.09 | H84: 562822.68
C85: 0.06 | D85: 3079958.1 | E85: 1745731.3 | F85: 1215336.1 | G85: 930554.54 | H85: 752881.57
C86: 0.07 | D86: -5801832.9 | E86: 12285254 | F86: 2967844.8 | G86: 1682785.6 | H86: 1171927.1
C87: 0.08 | D87: -1427219.4 | E87: -2269324.8 | F87: -5588521.4 | G87: 11837905 | H87: 2860807.5

Sheet ERROR CHECK
B2: ERROR CHECK
B4: =SUM(B6:B15) -> 0.06 | C4: MASTER ERROR CHECK
B6: =SUM('INCOME STATEMENT'!C16:N16) -> 0.06 | C6: TO CHECK EBITDA | D6: INCOME STATEMENT | E6: [Cell containing your listed EBITDA] - ([Cell for Revenue] - [Cell for Total Operating Expenses])
B7: =SUM('INCOME STATEMENT'!C22:N22) -> 0 | C7: TO CHECK EBITDA | E7: [Cell containing your listed EBIT] - ([Cell for EBITDA] - [Cell for D&A])
B8: =SUM('INCOME STATEMENT'!C36:N36) -> 0 | C8: TO CHECK PAT | E8: [Cell for PAT] - ([Cell for PBT] - [Cell for Tax] - [Cell for Loss from Disc. Ops])
B9: =SUM('BALANCE SHEET'!C32:I32) -> 0 | C9: TO CHECK ASSET - [EQUITY + LIABILITIES] | D9: BALANCE SHEET | E9: ASSET - [EQUITY + LIABILITIES]
B10: =SUM('CASH FLOW'!D33:J33) -> 0 | C10: TO CHECK CASH FLOW | D10: CASH FLOW | E10: ENDING CASH - CASH&CASH EQUIVALENT
B11: =SUM('FORCAST SCHEDULES'!C18:N18) -> 0 | C11: ERROR CHECK RESERVES | D11: FORCAST SCHEDULES | E11: ENDING RESERVE = BEGINNING RESERVE + NI - DIVIDENDS PAID

Sheet ASSUMPTIONS AND REASONING
B2: CATEGORY | C2: LINE ITEM | D2: ASSUMED VALUES | E2: REASONING
B3: INCOME STATEMENT | C3: REVENUE | D3: 0.21 | E3: "FY2026 REVENUE GROWTH FORECAST AT 21.0%, DERIVED FROM AN ~11.0% NOMINAL GDP GROWTH BASELINE PLUS A ~10.0% PREMIUM DRIVEN BY STRONG ANTICIPATED EXPANSION IN THE DERIVATIVES MARKET (EST. 20-25%+ GROWTH), CONTINUED FINANCIAL DEEPENING IN INDIA, AND ROBUST OVERALL MARKET PARTICIPATION."
D4: =D3-0.015 -> 0.195 | E4: ASSUMING LINEAR REDUCTION OF GRWOTH BY 1.5%
D5: =D4-0.015 -> 0.18 | E5: ASSUMING LINEAR REDUCTION OF GRWOTH BY 1.5%
D6: =D5-0.015 -> 0.165 | E6: ASSUMING LINEAR REDUCTION OF GRWOTH BY 1.5%
D7: =D6-0.015 -> 0.15 | E7: ASSUMING LINEAR REDUCTION OF GRWOTH BY 1.5%
C8: Other Expenses | D8: 0.1963 | E8: OTHER EXPENSES ARE PROJECTED AT 19.63% OF REVENUE, CALCULATED AS THE AVERAGE OF THE RATES FROM THE TWO MOST RECENT FISCAL YEARS (FY2024: 18.33%, FY2025: 20.93%). THIS APPROACH CAPTURES THE CURRENT OPERATIONAL COST STRUCTURE, WHICH INCLUDES LIKELY ONGOING INVESTMENTS IN TECHNOLOGY, BUSINESS DEVELOPMENT, AND COMPLIANCE CRUCIAL FOR A GROWING EXCHANGE, WHILE SMOOTHING OUT SINGLE-YEAR FLUCTUATIONS. IT IS ASSUMED THESE COSTS WILL SCALE PROPORTIONALLY WITH REVENUE, LEADING TO AN IMPLIED EBITDA MARGIN OF APPROXIMATELY 76.9%, CONSISTENT WITH NSE'S RECENT STRONG HISTORICAL PROFITABILITY.
C9: Contribution to Core SGF | D9: 0 | E9: THIS LINE ITEM IS HIGHLY VOLATILE AND NON-RECURRING IN HISTORICAL FINANCIALS (E.G., PERIODS OF ZERO AND NEGATIVE VALUES), INDICATING IT'S NOT A PREDICTABLE OPERATIONAL EXPENSE. CONTRIBUTIONS TO THE SGF ARE PRIMARILY DRIVEN BY REGULATORY REQUIREMENTS AND THE FUND'S OWN INTERNAL DYNAMICS (E.G., MEMBER CONTRIBUTIONS, INVESTMENT INCOME), NOT CONSISTENT CORE BUSINESS OPERATIONS. FOR VALUATION, MAINTAINING A CLEAN INCOME STATEMENT FOCUSED ON RECURRING OPERATING PROFITABILITY, WHILE ADDRESSING THE CRITICAL SGF BALANCE AS A BALANCE SHEET ITEM (TO BE LINKED TO DRIVERS LIKE TRADING VOLUMES AND REGULATORY NEEDS), IS THE MOST ACCURATE AND CONSERVATIVE MODELING PRACTICE. THIS APPROACH ENSURES TRANSPARENT BASE-CASE FINANCIALS, WITH SPECIFIC SGF ADJUSTMENTS TO BE ADDRESSED VIA THE BALANCE SHEET AND POTENTIALLY IN SCENARIO ANALYSIS.
C10: Loss from Discounted Operations | D10: 0 | E10: THIS LINE ITEM REPRESENTS GAINS OR LOSSES FROM BUSINESS SEGMENTS THAT HAVE BEEN SOLD, ABANDONED, OR HELD FOR SALE. ITS HIGHLY VOLATILE AND NON-RECURRING NATURE IN HISTORICAL FINANCIALS MAKES IT UNPREDICTABLE. FOR VALUATION, THE MOST ACCURATE AND CONSERVATIVE MODELING PRACTICE IS TO ASSUME A VALUE OF ZERO FOR ALL FORECASTED PERIODS. THIS APPROACH MAINTAINS A CLEAN INCOME STATEMENT FOCUSED ON PROJECTING RECURRING OPERATING PROFITABILITY FROM THE COMPANY'S CORE BUSINESS, ENSURING THAT THE FORECASTED EARNINGS TRULY REFLECT THE ONGOING FINANCIAL PERFORMANCE AND SUSTAINABLE EARNINGS POWER.
C11: Shares Outstading | D11: 247.5 | E11: FOR THE BASE-CASE VALUATION, WE ASSUME A CONSTANT NUMBER OF SHARES OUTSTANDING. THIS IS A STANDARD PRACTICE AS IT AVOIDS SPECULATING ON FUTURE CORPORATE ACTIONS LIKE SHARE BUYBACKS OR NEW ISSUANCES. A STOCK SPLIT, WHILE INCREASING THE NUMBER OF SHARES, DOES NOT CHANGE THE COMPANY'S FUNDAMENTAL VALUE AND THEREFORE WOULD BE A NON-MATERIAL EVENT FOR THE MODEL'S CORE VALUATION. THIS ASSUMPTION ENSURES THE MODEL IS FOCUSED ON THE INTRINSIC VALUE DRIVEN BY CORE BUSINESS PERFORMANCE.
B12: BALANCE SHEET | C12: EQUITY CAPITAL | D12: 247.5 | E12: FOR THE BASE-CASE VALUATION, WE ASSUME A CONSTANT EQUITY CAPITAL OF ₹247.50. THE FACE VALUE OF THE SHARES WAS ADJUSTED FROM ₹0.20 TO ₹1.00 IN 2025, AND WE WILL MAINTAIN THIS VALUE GOING FORWARD. THIS ENSURES THE MODEL REMAINS CONSISTENT WITH THE CURRENT CAPITAL STRUCTURE AND AVOIDS SPECULATING ON FUTURE CORPORATE ACTIONS.
C13: Share premium | D13: - | E13: HISTORICAL ADJUSTMENT (2025 ONLY): THE ₹198 CRORE ADJUSTMENT WAS MADE IN 2025 TO REFLECT A ONE-TIME HISTORICAL EVENT RELATED TO THE CONVERSION OF PREFERRED SHARES INTO COMMON EQUITY. THIS ADJUSTMENT ENSURES THE HISTORICAL BALANCE SHEET IS MATHEMATICALLY CONSISTENT AND PROVIDES A PROPER STARTING POINT FOR THE FORECAST. THE HISTORICAL DIVIDENDS PAID FOR 2025 WERE ALSO ADJUSTED TO EXCLUDE THIS NON-CASH CAPITAL TRANSACTION.
C15: Assets classified as held for sale | D15: 0 | E15: FOR THE FORECAST PERIOD, ASSETS CLASSIFIED AS HELD FOR SALE ARE ASSUMED TO BE ₹0. THIS IS A STANDARD BASE-CASE ASSUMPTION THAT REFLECTS THE NON-RECURRING NATURE OF THESE ASSETS AND THE EXPECTATION THAT THEY WILL BE SOLD, THUS NO LONGER APPEARING ON THE BALANCE SHEET.
